[{"province": "Araba/\u00c1lava", "absent": 67954, "census": 248453, "voters": 180499, "parties": [{"acronym": "PODEMOS-AHAL DUGU", "votes": 48265, "code": "PODEMOS", "name": "PODEMOS-AHAL DUGU", "seats": 1}, {"acronym": "PP", "votes": 33609, "code": "PP", "name": "PARTIDO POPULAR", "seats": 1}, {"acronym": "EAJ-PNV", "votes": 28297, "code": "PNV", "name": "EUZKO ALDERDI JELTZALEA-PARTIDO NACIONALISTA VASCO", "seats": 1}, {"acronym": "PSE-EE (PSOE)", "votes": 25293, "code": "PSOE", "name": "PARTIDO SOCIALISTA DE EUSKADI-EUSKADIKO EZKERRA (PSOE)", "seats": 1}, {"acronym": "EH Bildu", "votes": 21179, "code": "Bildu", "name": "EUSKAL HERRIA BILDU", "seats": 0}, {"acronym": "C's", "votes": 10468, "code": "C's", "name": "CIUDADANOS-PARTIDO DE LA CIUDADAN\u00cdA", "seats": 0}, {"acronym": "IU-UPeC", "votes": 6794, "code": "UP", "name": "UNIDAD POPULAR- ORAIN BATERA:EZKER ANITZA-IZQUIERDA UNIDA, UNIDAD POPULAR EN COM\u00daN", "seats": 0}, {"acronym": "PACMA", "votes": 1380, "code": "PACMA", "name": "PARTIDO ANIMALISTA CONTRA EL MALTRATO ANIMAL", "seats": 0}, {"acronym": "UPYD", "votes": 764, "code": "UPYD", "name": "UNI\u00d3N PROGRESO Y DEMOCRACIA", "seats": 0}, {"acronym": "RECORTES CERO-GRUPO VERDE", "votes": 558, "code": "Recortes Cero", "name": "RECORTES CERO-GRUPO VERDE", "seats": 0}, {"acronym": "EB - AZ", "votes": 470, "code": "EB", "name": "ESCA\u00d1OS EN BLANCO - AULKI ZURIAK", "seats": 0}, {"acronym": "PCPE", "votes": 175, "code": "PC", "name": "PARTIDO COMUNISTA DE LOS PUEBLOS DE ESPA\u00d1A", "seats": 0}, {"acronym": "OE", "votes": 110, "code": "OE", "name": "ONGI ETORRI", "seats": 0}, {"acronym": "Ln", "votes": 81, "code": "Ln", "name": "LIBERTAD NAVARRA-LIBERTATE NAFARRA", "seats": 0}], "community": "CA16", "province_number": "01", "totalseats": 4, "blank": 1290, "null": 1766}, {"province": "Albacete", "absent": 70717, "census": 304088, "voters": 233371, "parties": [{"acronym": "PP", "votes": 85152, "code": "PP", "name": "PARTIDO POPULAR", "seats": 2}, {"acronym": "PSOE", "votes": 65074, "code": "PSOE", "name": "PARTIDO SOCIALISTA OBRERO ESPA\u00d1OL", "seats": 1}, {"acronym": "C's", "votes": 33676, "code": "C's", "name": "CIUDADANOS-PARTIDO DE LA CIUDADAN\u00cdA", "seats": 1}, {"acronym": "PODEMOS", "votes": 32155, "code": "PODEMOS", "name": "PODEMOS", "seats": 0}, {"acronym": "UP-UPeC", "votes": 9277, "code": "UP", "name": "UNIDAD POPULAR: IZQUIERDA UNIDA, UNIDAD POPULAR EN COM\u00daN", "seats": 0}, {"acronym": "PACMA", "votes": 1573, "code": "PACMA", "name": "PARTIDO ANIMALISTA CONTRA EL MALTRATO ANIMAL", "seats": 0}, {"acronym": "UPYD", "votes": 1145, "code": "UPYD", "name": "UNI\u00d3N PROGRESO Y DEMOCRACIA", "seats": 0}, {"acronym": "VOX", "votes": 538, "code": "VOX", "name": "VOX", "seats": 0}, {"acronym": "RECORTES CERO-GRUPO VERDE", "votes": 305, "code": "Recortes Cero", "name": "RECORTES CERO-GRUPO VERDE", "seats": 0}, {"acronym": "PCPE", "votes": 246, "code": "PC", "name": "PARTIDO COMUNISTA DE LOS PUEBLOS DE ESPA\u00d1A", "seats": 0}, {"acronym": "PLD", "votes": 204, "code": "PLD", "name": "PARTIDO LIBERAL DE DERECHAS", "seats": 0}], "community": "CA08", "province_number": "02", "totalseats": 4, "blank": 1725, "null": 2301}, {"province": "Alicante/Alacant", "absent": 308915, "census": 1220001, "voters": 911086, "parties": [{"acronym": "PP", "votes": 296709, "code": "PP", "name": "PARTIDO POPULAR", "seats": 4}, {"acronym": "PODEMOS-COMPROM\u00cdS", "votes": 200885, "code": "PODEMOS", "name": "COMPROM\u00cdS-PODEMOS-\u00c9S EL MOMENT", "seats": 3}, {"acronym": "PSOE", "votes": 188367, "code": "PSOE", "name": "PARTIDO SOCIALISTA OBRERO ESPA\u00d1OL", "seats": 3}, {"acronym": "C's", "votes": 154037, "code": "C's", "name": "CIUDADANOS-PARTIDO DE LA CIUDADAN\u00cdA", "seats": 2}, {"acronym": "EUPV-UPeC", "votes": 33293, "code": "UP", "name": "UNITAT POPULAR:ESQUERRA UNIDA DEL PA\u00cdS VALENCI\u00c0, UNITAT POPULAR EN COM\u00daN  (EUPV-UPeC)", "seats": 0}, {"acronym": "PACMA", "votes": 8232, "code": "PACMA", "name": "PARTIDO ANIMALISTA CONTRA EL MALTRATO ANIMAL", "seats": 0}, {"acronym": "UPYD", "votes": 5552, "code": "UPYD", "name": "UNI\u00d3N PROGRESO Y DEMOCRACIA", "seats": 0}, {"acronym": "CENTRO MODERADO", "votes": 3254, "code": "CM", "name": "LOS VERDES-ECOPACIFISTAS", "seats": 0}, {"acronym": "VOX", "votes": 2223, "code": "VOX", "name": "VOX", "seats": 0}, {"acronym": "RECORTES CERO-GRUPO VERDE", "votes": 1751, "code": "Recortes Cero", "name": "RECORTES CERO-GRUPO VERDE", "seats": 0}, {"acronym": "PCPE", "votes": 1731, "code": "PC", "name": "PARTIDO COMUNISTA DE LOS PUEBLOS DE ESPA\u00d1A", "seats": 0}, {"acronym": "ARAPV", "votes": 606, "code": "ARAPV", "name": "ARA, PA\u00cdS VALENCI\u00c0", "seats": 0}, {"acronym": "FDEE", "votes": 454, "code": "FDEE", "name": "FORO DEM\u00d3CRATA", "seats": 0}, {"acronym": "P-LIB", "votes": 410, "code": "P-LIB", "name": "PARTIDO LIBERTARIO", "seats": 0}, {"acronym": "SOMVAL", "votes": 397, "code": "SOMVAL", "name": "SOM VALENCIANS", "seats": 0}], "community": "CA10", "province_number": "03", "totalseats": 12, "blank": 5291, "null": 7894}, {"province": "Almer\u00eda", "absent": 141531, "census": 452590, "voters": 311059, "parties": [{"acronym": "PP", "votes": 117407, "code": "PP", "name": "PARTIDO POPULAR", "seats": 2}, {"acronym": "PSOE", "votes": 89022, "code": "PSOE", "name": "PARTIDO SOCIALISTA OBRERO ESPA\u00d1OL", "seats": 2}, {"acronym": "C\u00b4s", "votes": 44320, "code": "C's", "name": "CIUDADANOS-PARTIDO DE LA CIUDADAN\u00cdA", "seats": 1}, {"acronym": "PODEMOS", "votes": 39482, "code": "PODEMOS", "name": "PODEMOS", "seats": 1}, {"acronym": "IULV-CA,UPeC", "votes": 10776, "code": "UP", "name": "UNIDAD POPULAR: IZQUIERDA UNIDA LOS VERDES-CONVOCATORIA POR ANDALUC\u00cdA, UNIDAD POPULAR EN COM\u00daN", "seats": 0}, {"acronym": "PACMA", "votes": 2092, "code": "PACMA", "name": "PARTIDO ANIMALISTA CONTRA EL MALTRATO ANIMAL", "seats": 0}, {"acronym": "UPYD", "votes": 1522, "code": "UPYD", "name": "UNI\u00d3N PROGRESO Y DEMOCRACIA", "seats": 0}, {"acronym": "VOX", "votes": 543, "code": "VOX", "name": "VOX", "seats": 0}, {"acronym": "FE de las JONS", "votes": 340, "code": "FE", "name": "FALANGE ESPA\u00d1OLA DE LAS JONS", "seats": 0}, {"acronym": "PCPE", "votes": 314, "code": "PC", "name": "PARTIDO COMUNISTA DE LOS PUEBLOS DE ESPA\u00d1A", "seats": 0}, {"acronym": "RECORTES CERO-GRUPO VERDE", "votes": 296, "code": "Recortes Cero", "name": "RECORTES CERO-GRUPO VERDE", "seats": 0}, {"acronym": "PUM+J", "votes": 172, "code": "PUM+J", "name": "POR UN MUNDO M\u00c1S JUSTO", "seats": 0}, {"acronym": "DN", "votes": 159, "code": "DN", "name": "DEMOCRACIA NACIONAL", "seats": 0}], "community": "CA01", "province_number": "04", "totalseats": 6, "blank": 2204, "null": 2410}, {"province": "\u00c1vila", "absent": 29770, "census": 132571, "voters": 102801, "parties": [{"acronym": "PP", "votes": 46963, "code": "PP", "name": "PARTIDO POPULAR", "seats": 2}, {"acronym": "PSOE", "votes": 20129, "code": "PSOE", "name": "PARTIDO SOCIALISTA OBRERO ESPA\u00d1OL", "seats": 1}, {"acronym": "C\u00b4s", "votes": 15892, "code": "C's", "name": "CIUDADANOS PARTIDO DE LA CIUDADAN\u00cdA", "seats": 0}, {"acronym": "PODEMOS", "votes": 11863, "code": "PODEMOS", "name": "PODEMOS", "seats": 0}, {"acronym": "IU-UPeC", "votes": 3878, "code": "UP", "name": "UNIDAD POPULAR: IZQUIERDA UNIDA, UNIDAD POPULAR EN COM\u00daN", "seats": 0}, {"acronym": "UPYD", "votes": 904, "code": "UPYD", "name": "UNI\u00d3N PROGRESO Y DEMOCRACIA", "seats": 0}, {"acronym": "PACMA", "votes": 512, "code": "PACMA", "name": "PARTIDO ANIMALISTA CONTRA EL MALTRATO ANIMAL", "seats": 0}, {"acronym": "VOX", "votes": 329, "code": "VOX", "name": "VOX", "seats": 0}, {"acronym": "FE de las JONS", "votes": 233, "code": "FE", "name": "FALANGE ESPA\u00d1OLA DE LAS JONS", "seats": 0}, {"acronym": "RECORTES CERO-GRUPO VERDE", "votes": 124, "code": "Recortes Cero", "name": "RECORTES CERO-GRUPO VERDE", "seats": 0}], "community": "CA07", "province_number": "05", "totalseats": 3, "blank": 742, "null": 1232}, {"province": "Badajoz", "absent": 144747, "census": 548693, "voters": 403946, "parties": [{"acronym": "PSOE", "votes": 148347, "code": "PSOE", "name": "PARTIDO SOCIALISTA OBRERO ESPA\u00d1OL", "seats": 3}, {"acronym": "PP", "votes": 137501, "code": "PP", "name": "PARTIDO POPULAR", "seats": 2}, {"acronym": "PODEMOS", "votes": 47203, "code": "PODEMOS", "name": "PODEMOS", "seats": 1}, {"acronym": "C's", "votes": 45252, "code": "C's", "name": "CIUDADANOS-PARTIDO DE LA CIUDADAN\u00cdA", "seats": 0}, {"acronym": "IU-UPeC", "votes": 12281, "code": "UP", "name": "UNIDAD POPULAR: IZQUIERDA UNIDA, UNIDAD POPULAR EN COM\u00daN", "seats": 0}, {"acronym": "PACMA", "votes": 2036, "code": "PACMA", "name": "PARTIDO ANIMALISTA CONTRA EL MALTRATO ANIMAL", "seats": 0}, {"acronym": "UPYD", "votes": 1539, "code": "UPYD", "name": "UNI\u00d3N PROGRESO Y DEMOCRACIA", "seats": 0}, {"acronym": "EU-eX", "votes": 948, "code": "EU-eX", "name": "EXTREMADURA UNIDA-EXTREME\u00d1OS", "seats": 0}, {"acronym": "RECORTES CERO-GRUPO VERDE", "votes": 505, "code": "Recortes Cero", "name": "RECORTES CERO-GRUPO VERDE", "seats": 0}], "community": "CA11", "province_number": "06", "totalseats": 6, "blank": 3112, "null": 5222}, {"province": "Balears, Illes", "absent": 260429, "census": 748560, "voters": 488131, "parties": [{"acronym": "PP", "votes": 140542, "code": "PP", "name": "PARTIDO POPULAR", "seats": 3}, {"acronym": "PODEMOS", "votes": 111416, "code": "PODEMOS", "name": "PODEMOS", "seats": 2}, {"acronym": "PSOE", "votes": 88542, "code": "PSOE", "name": "PARTIDO SOCIALISTA OBRERO ESPA\u00d1OL", "seats": 2}, {"acronym": "C's", "votes": 71446, "code": "C's", "name": "CIUDADANOS PARTIDO DE LA CIUDADAN\u00cdA", "seats": 1}, {"acronym": "M\u00c9S", "votes": 33931, "code": "MES", "name": "M\u00c9S", "seats": 0}, {"acronym": "EL PI", "votes": 12902, "code": "EL PI", "name": "EL PI - PROPOSTA PER LES ILLES", "seats": 0}, {"acronym": "UPB: IU-UPeC", "votes": 11434, "code": "UP", "name": "UNITAT POPULAR BALEARS: IZQUIERDA UNIDA, UNIDAD POPULAR EN COM\u00daN", "seats": 0}, {"acronym": "PACMA", "votes": 5106, "code": "PACMA", "name": "PARTIDO ANIMALISTA CONTRA EL MALTRATO ANIMAL", "seats": 0}, {"acronym": "UPYD", "votes": 2277, "code": "UPYD", "name": "UNI\u00d3N PROGRESO Y DEMOCRACIA", "seats": 0}, {"acronym": "RECORTES CERO-GRUPO VERDE", "votes": 1172, "code": "Recortes Cero", "name": "RECORTES CERO-GRUPO VERDE", "seats": 0}, {"acronym": "PFyV", "votes": 714, "code": "PFyV", "name": "PARTIDO FAMILIA Y VIDA", "seats": 0}], "community": "CA04", "province_number": "07", "totalseats": 8, "blank": 3971, "null": 4678}, {"province": "Barcelona", "absent": 1109443, "census": 3974403, "voters": 2864960, "parties": [{"acronym": "EN COM\u00da", "votes": 766889, "code": "PODEMOS", "name": "\"EN COM\u00da PODEM\"", "seats": 9}, {"acronym": "PSC-PSOE", "votes": 463612, "code": "PSOE", "name": "PARTIT DELS SOCIALISTES DE CATALUNYA", "seats": 5}, {"acronym": "ERC-CATS\u00cd", "votes": 412540, "code": "ERC", "name": "ESQUERRA REPUBLICANA DE CATALUNYA-CATALUNYA S\u00cd", "seats": 5}, {"acronym": "C's", "votes": 386143, "code": "C's", "name": "CIUTADANS-PARTIDO DE LA CIUDADAN\u00cdA", "seats": 4}, {"acronym": "DL", "votes": 377563, "code": "DL", "name": "DEMOCR\u00c0CIA I LLIBERTAT. CONVERG\u00c8NCIA. DEM\u00d2CRATES. REAGRUPAMENT", "seats": 4}, {"acronym": "PP", "votes": 321268, "code": "PP", "name": "PARTIDO POPULAR/PARTIT POPULAR", "seats": 4}, {"acronym": "unio.cat", "votes": 47743, "code": "Unio", "name": "UNI\u00d3 DEMOCR\u00c0TICA DE CATALUNYA", "seats": 0}, {"acronym": "PACMA", "votes": 34270, "code": "PACMA", "name": "PARTIT ANIMALISTA CONTRA EL MALTRACTAMENT ANIMAL", "seats": 0}, {"acronym": "RECORTES CERO-GRUPO VERDE", "votes": 10588, "code": "Recortes Cero", "name": "RECORTES CERO-GRUPO VERDE", "seats": 0}, {"acronym": "UPYD", "votes": 5859, "code": "UPYD", "name": "UNI\u00d3N PROGRESO Y DEMOCRACIA", "seats": 0}, {"acronym": "PCPC", "votes": 5363, "code": "PC", "name": "PARTIT COMUNISTA DEL POBLE DE CATALUNYA", "seats": 0}], "community": "CA09", "province_number": "08", "totalseats": 31, "blank": 18126, "null": 14996}, {"province": "Burgos", "absent": 67907, "census": 284915, "voters": 217008, "parties": [{"acronym": "PP", "votes": 81780, "code": "PP", "name": "PARTIDO POPULAR", "seats": 2}, {"acronym": "PSOE", "votes": 44488, "code": "PSOE", "name": "PARTIDO SOCIALISTA OBRERO ESPA\u00d1OL", "seats": 1}, {"acronym": "PODEMOS", "votes": 36612, "code": "PODEMOS", "name": "PODEMOS", "seats": 1}, {"acronym": "C\u00b4s", "votes": 33373, "code": "C's", "name": "CIUDADANOS-PARTIDO DE LA CIUDADAN\u00cdA", "seats": 0}, {"acronym": "IU-UPeC", "votes": 10099, "code": "UP", "name": "UNIDAD POPULAR: IZQUIERDA UNIDA, UNIDAD POPULAR EN COM\u00daN", "seats": 0}, {"acronym": "UPYD", "votes": 2259, "code": "UPYD", "name": "UNI\u00d3N PROGRESO Y DEMOCRACIA", "seats": 0}, {"acronym": "PACMA", "votes": 1420, "code": "PACMA", "name": "PARTIDO ANIMALISTA CONTRA EL MALTRATO ANIMAL", "seats": 0}, {"acronym": "VOX", "votes": 913, "code": "VOX", "name": "VOX", "seats": 0}, {"acronym": "PCPE", "votes": 504, "code": "PC", "name": "PARTIDO COMUNISTA DE LOS PUEBLOS DE ESPA\u00d1A", "seats": 0}, {"acronym": "SAIn", "votes": 497, "code": "SAIn", "name": "SOLIDARIDAD Y AUTOGESTI\u00d3N INTERNACIONALISTA", "seats": 0}, {"acronym": "RECORTES CERO-GRUPO VERDE", "votes": 447, "code": "Recortes Cero", "name": "RECORTES CERO-GRUPO VERDE", "seats": 0}, {"acronym": "IFem", "votes": 340, "code": "IFem", "name": "INICIATIVA FEMINISTA", "seats": 0}], "community": "CA07", "province_number": "09", "totalseats": 4, "blank": 2032, "null": 2244}, {"province": "C\u00e1ceres", "absent": 84233, "census": 335835, "voters": 251602, "parties": [{"acronym": "PP", "votes": 87729, "code": "PP", "name": "PARTIDO POPULAR", "seats": 2}, {"acronym": "PSOE", "votes": 84532, "code": "PSOE", "name": "PARTIDO SOCIALISTA OBRERO ESPA\u00d1OL", "seats": 2}, {"acronym": "PODEMOS", "votes": 34552, "code": "PODEMOS", "name": "PODEMOS", "seats": 0}, {"acronym": "C's", "votes": 28293, "code": "C's", "name": "CIUDADANOS-PARTIDO DE LA CIUDADAN\u00cdA", "seats": 0}, {"acronym": "IU-UPeC", "votes": 7216, "code": "UP", "name": "UNIDAD POPULAR: IZQUIERDA UNIDA-UNIDAD POPULAR EN COM\u00daN", "seats": 0}, {"acronym": "PACMA", "votes": 1349, "code": "PACMA", "name": "PARTIDO ANIMALISTA CONTRA EL MALTRATO ANIMAL", "seats": 0}, {"acronym": "UPYD", "votes": 1071, "code": "UPYD", "name": "UNI\u00d3N PROGRESO Y DEMOCRACIA", "seats": 0}, {"acronym": "EU-eX", "votes": 1047, "code": "EU-eX", "name": "EXTREMADURA UNIDA-EXTREME\u00d1OS", "seats": 0}, {"acronym": "VOX", "votes": 511, "code": "VOX", "name": "VOX", "seats": 0}, {"acronym": "RECORTES CERO-GRUPO VERDE", "votes": 334, "code": "Recortes Cero", "name": "RECORTES CERO-GRUPO VERDE", "seats": 0}], "community": "CA11", "province_number": "10", "totalseats": 4, "blank": 1556, "null": 3412}, {"province": "C\u00e1diz", "absent": 317096, "census": 968095, "voters": 650999, "parties": [{"acronym": "PSOE", "votes": 180667, "code": "PSOE", "name": "PARTIDO SOCIALISTA OBRERO ESPA\u00d1OL", "seats": 3}, {"acronym": "PP", "votes": 179054, "code": "PP", "name": "PARTIDO POPULAR", "seats": 3}, {"acronym": "PODEMOS", "votes": 130215, "code": "PODEMOS", "name": "PODEMOS", "seats": 2}, {"acronym": "C's", "votes": 94707, "code": "C's", "name": "CIUDADANOS-PARTIDO DE LA CIUDADAN\u00cdA", "seats": 1}, {"acronym": "IULV-CA, UPeC", "votes": 38798, "code": "UP", "name": "UNIDAD POPULAR: IZQUIERDA UNIDA LOS VERDES-CONVOCATORIA POR ANDALUC\u00cdA, UNIDAD POPULAR EN COM\u00daN", "seats": 0}, {"acronym": "PACMA", "votes": 7569, "code": "PACMA", "name": "PARTIDO ANIMALISTA CONTRA EL MALTRATO ANIMAL", "seats": 0}, {"acronym": "UPYD", "votes": 3623, "code": "UPYD", "name": "UNI\u00d3N PROGRESO Y DEMOCRACIA", "seats": 0}, {"acronym": "VOX", "votes": 1486, "code": "VOX", "name": "VOX", "seats": 0}, {"acronym": "RECORTES CERO-GRUPO VERDE", "votes": 1041, "code": "Recortes Cero", "name": "RECORTES CERO-GRUPO VERDE", "seats": 0}, {"acronym": "PCPE", "votes": 778, "code": "PC", "name": "PARTIDO COMUNISTA DE LOS PUEBLOS DE ESPA\u00d1A", "seats": 0}, {"acronym": "P-LIB", "votes": 422, "code": "P-LIB", "name": "PARTIDO LIBERTARIO", "seats": 0}], "community": "CA01", "province_number": "11", "totalseats": 9, "blank": 6779, "null": 5860}, {"province": "Castell\u00f3n/Castell\u00f3", "absent": 97386, "census": 409465, "voters": 312079, "parties": [{"acronym": "PP", "votes": 98341, "code": "PP", "name": "PARTIDO POPULAR", "seats": 2}, {"acronym": "PODEMOS - COMPROMIS", "votes": 74457, "code": "PODEMOS", "name": "COMPROM\u00cdS-PODEMOS-\u00c9S EL MOMENT", "seats": 1}, {"acronym": "PSOE", "votes": 66450, "code": "PSOE", "name": "PARTIDO SOCIALISTA OBRERO ESPA\u00d1OL", "seats": 1}, {"acronym": "C's", "votes": 48220, "code": "C's", "name": "CIUDADANOS-PARTIDO DE LA CIUDADAN\u00cdA", "seats": 1}, {"acronym": "EUPV-UPeC", "votes": 9565, "code": "UP", "name": "UNITAT POPULAR: ESQUERRA UNIDA DEL PA\u00cdS VALENCI\u00c0, UNITAT POPULAR EN COMU", "seats": 0}, {"acronym": "PACMA", "votes": 2239, "code": "PACMA", "name": "PARTIDO ANIMALISTA CONTRA EL MALTRATO ANIMAL", "seats": 0}, {"acronym": "CCD", "votes": 2134, "code": "CCD", "name": "CIUDADANOS DE CENTRO DEMOCR\u00c1TICO", "seats": 0}, {"acronym": "UPYD", "votes": 1739, "code": "UPYD", "name": "UNI\u00d3N PROGRESO Y DEMOCRACIA", "seats": 0}, {"acronym": "VOX", "votes": 919, "code": "VOX", "name": "VOX", "seats": 0}, {"acronym": "PCPE", "votes": 505, "code": "PC", "name": "PARTIT COMUNISTA DELS POBLES D\u2019ESPANYA", "seats": 0}, {"acronym": "RECORTES CERO-GRUPO VERDE", "votes": 484, "code": "Recortes Cero", "name": "RECORTES CERO-GRUPO VERDE", "seats": 0}, {"acronym": "DN", "votes": 469, "code": "DN", "name": "DEMOCRACIA NACIONAL", "seats": 0}, {"acronym": "SOMVAL", "votes": 466, "code": "SOMVAL", "name": "SOM VALENCIANS", "seats": 0}, {"acronym": "ARAPV", "votes": 412, "code": "ARAPV", "name": "ARA, PA\u00cdS VALENCI\u00c0", "seats": 0}, {"acronym": "IFem", "votes": 255, "code": "IFem", "name": "INICIATIVA FEMINISTA", "seats": 0}], "community": "CA10", "province_number": "12", "totalseats": 5, "blank": 2090, "null": 3334}, {"province": "Ciudad Real", "absent": 97789, "census": 396290, "voters": 298501, "parties": [{"acronym": "PP", "votes": 113356, "code": "PP", "name": "PARTIDO POPULAR", "seats": 3}, {"acronym": "PSOE", "votes": 91860, "code": "PSOE", "name": "PARTIDO SOCIALISTA OBRERO ESPA\u00d1OL", "seats": 2}, {"acronym": "PODEMOS", "votes": 36724, "code": "PODEMOS", "name": "PODEMOS", "seats": 0}, {"acronym": "C's", "votes": 36377, "code": "C's", "name": "CIUDADANOS-PARTIDO DE LA CIUDADAN\u00cdA", "seats": 0}, {"acronym": "IU-UPeC", "votes": 9801, "code": "UP", "name": "UNIDAD POPULAR: IZQUIERDA UNIDA, UNIDAD POPULAR EN COM\u00daN", "seats": 0}, {"acronym": "PACMA", "votes": 1940, "code": "PACMA", "name": "PARTIDO ANIMALISTA-CONTRA EL MALTRATO ANIMAL", "seats": 0}, {"acronym": "UPYD", "votes": 1618, "code": "UPYD", "name": "UNI\u00d3N PROGRESO Y DEMOCRACIA", "seats": 0}, {"acronym": "VOX", "votes": 559, "code": "VOX", "name": "VOX", "seats": 0}, {"acronym": "RECORTES CERO-GRUPO VERDE", "votes": 383, "code": "Recortes Cero", "name": "RECORTES CERO-GRUPO VERDE", "seats": 0}, {"acronym": "DN", "votes": 174, "code": "DN", "name": "DEMOCRACIA NACIONAL", "seats": 0}], "community": "CA08", "province_number": "13", "totalseats": 5, "blank": 2282, "null": 3427}, {"province": "C\u00f3rdoba", "absent": 163357, "census": 635085, "voters": 471728, "parties": [{"acronym": "PSOE", "votes": 149628, "code": "PSOE", "name": "PARTIDO SOCIALISTA OBRERO ESPA\u00d1OL", "seats": 2}, {"acronym": "PP", "votes": 141917, "code": "PP", "name": "PARTIDO POPULAR", "seats": 2}, {"acronym": "PODEMOS", "votes": 68451, "code": "PODEMOS", "name": "PODEMOS", "seats": 1}, {"acronym": "C\u00b4s", "votes": 55655, "code": "C's", "name": "CIUDADANOS-PARTIDO DE LA CIUDADAN\u00cdA", "seats": 1}, {"acronym": "IULV-CA, UPeC", "votes": 37564, "code": "UP", "name": "UNIDAD POPULAR: IZQUIERDA UNIDA LOS VERDES-CONVOCATORIA POR ANDALUC\u00cdA, UNIDAD POPULAR EN COM\u00daN", "seats": 0}, {"acronym": "PACMA", "votes": 3523, "code": "PACMA", "name": "PARTIDO ANIMALISTA CONTRA EL MALTRATO ANIMAL", "seats": 0}, {"acronym": "UPYD", "votes": 2060, "code": "UPYD", "name": "UNI\u00d3N PROGRESO Y DEMOCRACIA", "seats": 0}, {"acronym": "PCPE", "votes": 874, "code": "PC", "name": "PARTIDO COMUNISTA DE LOS PUEBLOS DE ESPA\u00d1A", "seats": 0}, {"acronym": "PCOE", "votes": 810, "code": "PC", "name": "PARTIDO COMUNISTA OBRERO ESPA\u00d1OL", "seats": 0}, {"acronym": "EB", "votes": 626, "code": "EB", "name": "ESCA\u00d1OS EN BLANCO", "seats": 0}, {"acronym": "RECORTES CERO-GRUPO VERDE", "votes": 601, "code": "Recortes Cero", "name": "RECORTES CERO-GRUPO VERDE", "seats": 0}, {"acronym": "FE de las JONS", "votes": 494, "code": "FE", "name": "FALANGE ESPA\u00d1OLA DE LAS JONS", "seats": 0}], "community": "CA01", "province_number": "14", "totalseats": 6, "blank": 4481, "null": 5044}, {"province": "Coru\u00f1a, A", "absent": 257840, "census": 936602, "voters": 678762, "parties": [{"acronym": "PP", "votes": 237837, "code": "PP", "name": "PARTIDO POPULAR", "seats": 3}, {"acronym": "PODEMOS-En Marea-ANOVA-EU", "votes": 176625, "code": "PODEMOS", "name": "EN MAREA", "seats": 2}, {"acronym": "PSdeG-PSOE", "votes": 136931, "code": "PSOE", "name": "PARTIDO DOS SOCIALISTAS DE GALICIA-PSOE", "seats": 2}, {"acronym": "C's", "votes": 66395, "code": "C's", "name": "CIUDADANOS-PARTIDO DE LA CIUDADAN\u00cdA", "seats": 1}, {"acronym": "N\u00d3S", "votes": 30488, "code": "BNG", "name": "N\u00d3S-CANDIDATURA GALEGA (BNG-CG-FOGA-PCPG-PG)", "seats": 0}, {"acronym": "PACMA", "votes": 5078, "code": "PACMA", "name": "PARTIDO ANIMALISTA CONTRA O MALTRATO ANIMAL", "seats": 0}, {"acronym": "UPYD", "votes": 3493, "code": "UPYD", "name": "UNI\u00d3N PROGRESO Y DEMOCRACIA", "seats": 0}, {"acronym": "RECORTES CERO-GRUPO VERDE", "votes": 1527, "code": "Recortes Cero", "name": "RECORTES CERO-GRUPO VERDE", "seats": 0}, {"acronym": "PCPE", "votes": 1438, "code": "PC", "name": "COMUNISTAS DA GALIZA", "seats": 0}, {"acronym": "VOX", "votes": 1239, "code": "VOX", "name": "VOX", "seats": 0}, {"acronym": "PT", "votes": 1096, "code": "PT", "name": "PARTIDO DA TERRA", "seats": 0}, {"acronym": "SAIn", "votes": 422, "code": "SAIn", "name": "SOLIDARIDAD Y AUTOGESTI\u00d3N INTERNACIONALISTA", "seats": 0}], "community": "CA12", "province_number": "15", "totalseats": 8, "blank": 7643, "null": 8550}, {"province": "Cuenca", "absent": 33812, "census": 156086, "voters": 122274, "parties": [{"acronym": "PP", "votes": 50695, "code": "PP", "name": "PARTIDO POPULAR", "seats": 2}, {"acronym": "PSOE", "votes": 36973, "code": "PSOE", "name": "PARTIDO SOCIALISTA OBRERO ESPA\u00d1OL", "seats": 1}, {"acronym": "PODEMOS", "votes": 14057, "code": "PODEMOS", "name": "PODEMOS", "seats": 0}, {"acronym": "C's", "votes": 13015, "code": "C's", "name": "CIUDADANOS-PARTIDO DE LA CIUDADAN\u00cdA", "seats": 0}, {"acronym": "IU-UPeC", "votes": 3614, "code": "UP", "name": "UNIDAD POPULAR: IZQUIERDA UNIDA, UNIDAD POPULAR EN COM\u00daN", "seats": 0}, {"acronym": "PACMA", "votes": 533, "code": "PACMA", "name": "PARTIDO ANIMALISTA CONTRA EL MALTRATO ANIMAL", "seats": 0}, {"acronym": "UPYD", "votes": 462, "code": "UPYD", "name": "UNI\u00d3N PROGRESO Y DEMOCRACIA", "seats": 0}, {"acronym": "VOX", "votes": 353, "code": "VOX", "name": "VOX", "seats": 0}, {"acronym": "RECORTES CERO-GRUPO VERDE", "votes": 165, "code": "Recortes Cero", "name": "RECORTES CERO-GRUPO VERDE", "seats": 0}, {"acronym": "PCPE", "votes": 96, "code": "PC", "name": "PARTIDO COMUNISTA DE LOS PUEBLOS DE ESPA\u00d1A", "seats": 0}], "community": "CA08", "province_number": "16", "totalseats": 3, "blank": 929, "null": 1382}, {"province": "Girona", "absent": 161689, "census": 496127, "voters": 334438, "parties": [{"acronym": "DL", "votes": 82984, "code": "DL", "name": "DEMOCR\u00c0CIA I LLIBERTAT. CONVERG\u00c8NCIA. DEM\u00d2CRATES. REAGRUPAMENT", "seats": 2}, {"acronym": "ERC-CATS\u00cd", "votes": 77710, "code": "ERC", "name": "ESQUERRA REPUBLICANA DE CATALUNYA-CATALUNYA S\u00cd", "seats": 2}, {"acronym": "EN COM\u00da", "votes": 53894, "code": "PODEMOS", "name": "EN COM\u00da PODEM", "seats": 1}, {"acronym": "PSC-PSOE", "votes": 41972, "code": "PSOE", "name": "PARTIT DELS SOCIALISTES DE CATALUNYA", "seats": 1}, {"acronym": "C's", "votes": 32648, "code": "C's", "name": "CIUTADANS - PARTIDO DE LA CIUDADAN\u00cdA", "seats": 0}, {"acronym": "PP", "votes": 28281, "code": "PP", "name": "PARTIDO POPULAR", "seats": 0}, {"acronym": "unio.cat", "votes": 5845, "code": "Unio", "name": "UNI\u00d3 DEMOCR\u00c0TICA DE CATALUNYA", "seats": 0}, {"acronym": "PACMA", "votes": 3610, "code": "PACMA", "name": "PARTIT ANIMALISTA CONTRA EL MALTRACTAMENT ANIMAL", "seats": 0}, {"acronym": "RECORTES CERO-GRUPO VERDE", "votes": 876, "code": "Recortes Cero", "name": "RECORTES CERO-GRUPO VERDE", "seats": 0}, {"acronym": "PCPC", "votes": 595, "code": "PC", "name": "PARTIT COMUNISTA DEL POBLE DE CATALUNYA", "seats": 0}, {"acronym": "UPYD", "votes": 582, "code": "UPYD", "name": "UNI\u00d3N PROGRESO Y DEMOCRACIA", "seats": 0}], "community": "CA09", "province_number": "17", "totalseats": 6, "blank": 2507, "null": 2934}, {"province": "Granada", "absent": 190271, "census": 702885, "voters": 512614, "parties": [{"acronym": "PP", "votes": 158328, "code": "PP", "name": "PARTIDO POPULAR", "seats": 3}, {"acronym": "PSOE", "votes": 157585, "code": "PSOE", "name": "PARTIDO SOCIALISTA OBRERO ESPA\u00d1OL", "seats": 2}, {"acronym": "PODEMOS", "votes": 83051, "code": "PODEMOS", "name": "PODEMOS", "seats": 1}, {"acronym": "C\u00b4s", "votes": 70597, "code": "C's", "name": "CIUDADANOS PARTIDO DE LA CIUDADAN\u00cdA", "seats": 1}, {"acronym": "UP: IULV-CA, UPeC", "votes": 25895, "code": "UP", "name": "UNIDAD POPULAR: IZQUIERDA UNIDA LOS VERDES - CONVOCATORIA POR ANDALUC\u00cdA, UNIDAD POPULAR EN COM\u00daN", "seats": 0}, {"acronym": "PACMA", "votes": 3796, "code": "PACMA", "name": "PARTIDO ANIMALISTA CONTRA EL MALTRATO ANIMAL", "seats": 0}, {"acronym": "UPYD", "votes": 2666, "code": "UPYD", "name": "UNI\u00d3N PROGRESO Y DEMOCRACIA", "seats": 0}, {"acronym": "VOX", "votes": 1264, "code": "VOX", "name": "VOX", "seats": 0}, {"acronym": "PCPE", "votes": 692, "code": "PC", "name": "PARTIDO COMUNISTA DE LOS PUEBLOS DE ESPA\u00d1A", "seats": 0}, {"acronym": "RECORTES CERO-GRUPO VERDE", "votes": 637, "code": "Recortes Cero", "name": "RECORTES CERO-GRUPO VERDE", "seats": 0}, {"acronym": "PUM+J", "votes": 441, "code": "PUM+J", "name": "POR UN MUNDO M\u00c1S JUSTO", "seats": 0}], "community": "CA01", "province_number": "18", "totalseats": 7, "blank": 3425, "null": 4237}, {"province": "Guadalajara", "absent": 41209, "census": 178745, "voters": 137536, "parties": [{"acronym": "PP", "votes": 47299, "code": "PP", "name": "PARTIDO POPULAR", "seats": 1}, {"acronym": "PSOE", "votes": 30639, "code": "PSOE", "name": "PARTIDO SOCIALISTA OBRERO ESPA\u00d1OL", "seats": 1}, {"acronym": "C's", "votes": 24554, "code": "C's", "name": "CIUDADANOS PARTIDO DE LA CIUDADAN\u00cdA", "seats": 1}, {"acronym": "PODEMOS", "votes": 23736, "code": "PODEMOS", "name": "PODEMOS", "seats": 0}, {"acronym": "IU-UPeC", "votes": 5605, "code": "UP", "name": "UNIDAD POPULAR: IZQUIERDA UNIDA, UNIDAD POPULAR EN COM\u00daN", "seats": 0}, {"acronym": "PACMA", "votes": 1144, "code": "PACMA", "name": "PARTIDO ANIMALISTA CONTRA EL MALTRATO ANIMAL", "seats": 0}, {"acronym": "UPYD", "votes": 1020, "code": "UPYD", "name": "UNI\u00d3N PROGRESO Y DEMOCRACIA", "seats": 0}, {"acronym": "VOX", "votes": 643, "code": "VOX", "name": "VOX", "seats": 0}, {"acronym": "RECORTES CERO-GRUPO VERDE", "votes": 282, "code": "Recortes Cero", "name": "RECORTES CERO-GRUPO VERDE", "seats": 0}, {"acronym": "SAIn", "votes": 75, "code": "SAIn", "name": "SOLIDARIDAD Y AUTOGESTI\u00d3N INTERNACIONALISTA", "seats": 0}], "community": "CA08", "province_number": "19", "totalseats": 3, "blank": 977, "null": 1562}, {"province": "Gipuzkoa", "absent": 166211, "census": 555416, "voters": 389205, "parties": [{"acronym": "PODEMOS-AHAL DUGU", "votes": 97859, "code": "PODEMOS", "name": "PODEMOS-AHAL DUGU", "seats": 2}, {"acronym": "EAJ-PNV", "votes": 91043, "code": "PNV", "name": "EUZKO ALDERDI JELTZALEA-PARTIDO NACIONALISTA VASCO (EAJ-PNV)", "seats": 2}, {"acronym": "EH Bildu", "votes": 80880, "code": "Bildu", "name": "EUSKAL HERRIA BILDU (EH Bildu)", "seats": 1}, {"acronym": "PSE-EE", "votes": 51530, "code": "PSOE", "name": "PARTIDO SOCIALISTA DE EUSKADI-EUSKADIKO EZKERRA (PSOE)", "seats": 1}, {"acronym": "PP", "votes": 33668, "code": "PP", "name": "PARTIDO POPULAR (PP)", "seats": 0}, {"acronym": "C's", "votes": 14419, "code": "C's", "name": "CIUDADANOS-PARTIDO DE LA CIUDADAN\u00cdA (C's)", "seats": 0}, {"acronym": "IU-UPeC", "votes": 10630, "code": "UP", "name": "UNIDAD POPULAR-ORAIN BATERA:EZKER ANITZA-IZQUIERDA UNIDA,UNIDAD POPULAR EN COM\u00daN.(IU-UPeC)", "seats": 0}, {"acronym": "PACMA", "votes": 2259, "code": "PACMA", "name": "PARTIDO ANIMALISTA CONTRA EL MALTRATO ANIMAL (PACMA)", "seats": 0}, {"acronym": "UPYD", "votes": 1293, "code": "UPYD", "name": "UNI\u00d3N PROGRESO Y DEMOCRACIA (UPYD)", "seats": 0}, {"acronym": "RECORTES CERO-GRUPO VERDE", "votes": 774, "code": "Recortes Cero", "name": "RECORTES CERO-GRUPO VERDE", "seats": 0}, {"acronym": "Ln", "votes": 367, "code": "Ln", "name": "LIBERTAD NAVARRA, LIBERTATE NAFARRA (Ln)", "seats": 0}], "community": "CA16", "province_number": "20", "totalseats": 6, "blank": 2527, "null": 1956}, {"province": "Huelva", "absent": 127992, "census": 389804, "voters": 261812, "parties": [{"acronym": "PSOE", "votes": 95592, "code": "PSOE", "name": "PARTIDO SOCIALISTA OBRERO ESPA\u00d1OL", "seats": 2}, {"acronym": "PP", "votes": 74479, "code": "PP", "name": "PARTIDO POPULAR", "seats": 2}, {"acronym": "PODEMOS", "votes": 39349, "code": "PODEMOS", "name": "PODEMOS", "seats": 1}, {"acronym": "C's", "votes": 30709, "code": "C's", "name": "CIUDADANOS, PARTIDO DE LA CIUDADAN\u00cdA", "seats": 0}, {"acronym": "IULV-CA,UPeC", "votes": 11529, "code": "UP", "name": "UNIDAD POPULAR: IZQUIERDA UNIDA LOS VERDES-CONVOCATORIA POR ANDALUC\u00cdA, UNIDAD POPULAR EN COM\u00daN", "seats": 0}, {"acronym": "PACMA", "votes": 2376, "code": "PACMA", "name": "PARTIDO ANIMALISTA CONTRA EL MALTRATO ANIMAL", "seats": 0}, {"acronym": "UPYD", "votes": 1005, "code": "UPYD", "name": "UNI\u00d3N PROGRESO Y DEMOCRACIA", "seats": 0}, {"acronym": "VOX", "votes": 461, "code": "VOX", "name": "VOX", "seats": 0}, {"acronym": "RECORTES CERO-GRUPO VERDE", "votes": 376, "code": "Recortes Cero", "name": "RECORTES CERO-GRUPO VERDE", "seats": 0}, {"acronym": "PCPE", "votes": 294, "code": "PC", "name": "PARTIDO COMUNISTA DE LOS PUEBLOS DE ESPA\u00d1A", "seats": 0}, {"acronym": "DN", "votes": 192, "code": "DN", "name": "DEMOCRACIA NACIONAL", "seats": 0}], "community": "CA01", "province_number": "21", "totalseats": 5, "blank": 2389, "null": 3061}, {"province": "Huesca", "absent": 44596, "census": 167329, "voters": 122733, "parties": [{"acronym": "PP-PAR", "votes": 39631, "code": "PP", "name": "PARTIDO POPULAR EN COALICI\u00d3N CON EL PARTIDO ARAGON\u00c9S", "seats": 1}, {"acronym": "PSOE", "votes": 30039, "code": "PSOE", "name": "PARTIDO SOCIALISTA OBRERO ESPA\u00d1OL", "seats": 1}, {"acronym": "PODEMOS-Ahora Alto Arag\u00f3n en Com\u00fan", "votes": 21768, "code": "PODEMOS", "name": "PODEMOS-Ahora Alto Arag\u00f3n en Com\u00fan", "seats": 1}, {"acronym": "C's", "votes": 19703, "code": "C's", "name": "CIUDADANOS PARTIDO DE LA CIUDADAN\u00cdA", "seats": 0}, {"acronym": "IU-CHA-UPeC", "votes": 6400, "code": "UP", "name": "UNIDAD POPULAR EN ARAG\u00d3N: IZQUIERDA UNIDA, CHUNTA ARAGONESISTA, UNIDAD POPULAR EN COM\u00daN", "seats": 0}, {"acronym": "UPYD", "votes": 847, "code": "UPYD", "name": "UNI\u00d3N PROGRESO Y DEMOCRACIA", "seats": 0}, {"acronym": "PACMA", "votes": 785, "code": "PACMA", "name": "PARTIDO ANIMALISTA CONTRA EL MALTRATO ANIMAL", "seats": 0}, {"acronym": "EB", "votes": 547, "code": "EB", "name": "ESCA\u00d1OS EN BLANCO", "seats": 0}, {"acronym": "PCPE", "votes": 253, "code": "PC", "name": "PARTIDO COMUNISTA DE LOS PUEBLOS DE ESPA\u00d1A", "seats": 0}, {"acronym": "RECORTES CERO-GRUPO VERDE", "votes": 248, "code": "Recortes Cero", "name": "RECORTES CERO-GRUPO VERDE", "seats": 0}, {"acronym": "Independientes-FIA", "votes": 113, "code": "FIA", "name": "INDEPENDIENTES POR ARAG\u00d3N", "seats": 0}], "community": "CA02", "province_number": "22", "totalseats": 3, "blank": 1249, "null": 1150}, {"province": "Ja\u00e9n", "absent": 131429, "census": 522170, "voters": 390741, "parties": [{"acronym": "PSOE", "votes": 148397, "code": "PSOE", "name": "PARTIDO SOCIALISTA OBRERO ESPA\u00d1OL", "seats": 3}, {"acronym": "PP", "votes": 121850, "code": "PP", "name": "PARTIDO POPULAR", "seats": 2}, {"acronym": "PODEMOS", "votes": 48362, "code": "PODEMOS", "name": "PODEMOS", "seats": 0}, {"acronym": "C's", "votes": 41298, "code": "C's", "name": "CIUDADANOS-PARTIDO DE LA CIUDADAN\u00cdA", "seats": 0}, {"acronym": "IULV-CA,UPeC", "votes": 16719, "code": "UP", "name": "UNIDAD POPULAR: IZQUIERDA UNIDA LOS VERDES-CONVOCATORIA POR ANDALUC\u00cdA, UNIDAD POPULAR EN COM\u00daN", "seats": 0}, {"acronym": "PACMA", "votes": 2536, "code": "PACMA", "name": "PARTIDO ANIMALISTA CONTRA EL MALTRATO ANIMAL", "seats": 0}, {"acronym": "UPYD", "votes": 1278, "code": "UPYD", "name": "UNI\u00d3N PROGRESO Y DEMOCRACIA", "seats": 0}, {"acronym": "CILUS", "votes": 1188, "code": "CILUS", "name": "CIUDADANOS LIBRES UNIDOS", "seats": 0}, {"acronym": "AJU", "votes": 771, "code": "AJU", "name": "ANDALUCES DE JA\u00c9N UNIDOS", "seats": 0}, {"acronym": "VOX", "votes": 710, "code": "VOX", "name": "VOX", "seats": 0}, {"acronym": "PCPE", "votes": 467, "code": "PC", "name": "PARTIDO COMUNISTA DE LOS PUEBLOS DE ESPA\u00d1A", "seats": 0}, {"acronym": "RECORTES CERO-GRUPO VERDE", "votes": 369, "code": "Recortes Cero", "name": "RECORTES CERO-GRUPO VERDE", "seats": 0}, {"acronym": "SAIn", "votes": 197, "code": "SAIn", "name": "SOLIDARIDAD Y AUTOGESTI\u00d3N INTERNACIONALISTA", "seats": 0}], "community": "CA01", "province_number": "23", "totalseats": 5, "blank": 2713, "null": 3886}, {"province": "Le\u00f3n", "absent": 104571, "census": 398414, "voters": 293843, "parties": [{"acronym": "PP", "votes": 103458, "code": "PP", "name": "PARTIDO POPULAR", "seats": 2}, {"acronym": "PSOE", "votes": 73685, "code": "PSOE", "name": "PARTIDO SOCIALISTA OBRERO ESPA\u00d1OL", "seats": 1}, {"acronym": "PODEMOS", "votes": 50968, "code": "PODEMOS", "name": "PODEMOS", "seats": 1}, {"acronym": "C's", "votes": 37671, "code": "C's", "name": "CIUDADANOS PARTIDO DE LA CIUDADAN\u00cdA", "seats": 1}, {"acronym": "IU-UPeC", "votes": 13929, "code": "UP", "name": "UNIDAD POPULAR: IZQUIERDA UNIDA, UNIDAD POPULAR EN COM\u00daN", "seats": 0}, {"acronym": "UPYD", "votes": 2023, "code": "UPYD", "name": "UNI\u00d3N PROGRESO Y DEMOCRACIA", "seats": 0}, {"acronym": "PACMA", "votes": 1803, "code": "PACMA", "name": "PARTIDO ANIMALISTA CONTRA EL MALTRATO ANIMAL", "seats": 0}, {"acronym": "CRA", "votes": 1027, "code": "CRA", "name": "CIUDADANOS RURALES AGRUPADOS", "seats": 0}, {"acronym": "PREPAL", "votes": 894, "code": "PREPAL", "name": "PARTIDO REGIONALISTA DEL PA\u00cdS LEON\u00c9S", "seats": 0}, {"acronym": "VOX", "votes": 738, "code": "VOX", "name": "VOX", "seats": 0}, {"acronym": "PCPE", "votes": 528, "code": "PC", "name": "PARTIDO COMUNISTA DE LOS PUEBLOS DE ESPA\u00d1A", "seats": 0}, {"acronym": "RECORTES CERO-GRUPO VERDE", "votes": 471, "code": "Recortes Cero", "name": "RECORTES CERO-GRUPO VERDE", "seats": 0}, {"acronym": "DN", "votes": 305, "code": "DN", "name": "DEMOCRACIA NACIONAL", "seats": 0}], "community": "CA07", "province_number": "24", "totalseats": 5, "blank": 2939, "null": 3404}, {"province": "Lleida", "absent": 99536, "census": 299069, "voters": 199533, "parties": [{"acronym": "DL", "votes": 48005, "code": "DL", "name": "DEMOCR\u00c0CIA I LLIBERTAT. CONVERG\u00c8NCIA. DEM\u00d2CRATES. REAGRUPAMENT", "seats": 1}, {"acronym": "ERC-CATSI", "votes": 44002, "code": "ERC", "name": "ESQUERRA REPUBLICANA DE CATALUNYA-CATALUNYA S\u00cd", "seats": 1}, {"acronym": "EN COM\u00da", "votes": 30329, "code": "PODEMOS", "name": "EN COM\u00da PODEM", "seats": 1}, {"acronym": "PSC-PSOE", "votes": 24650, "code": "PSOE", "name": "PARTIT DELS SOCIALISTES DE CATALUNYA", "seats": 1}, {"acronym": "PP", "votes": 22260, "code": "PP", "name": "PARTIDO POPULAR", "seats": 0}, {"acronym": "C's", "votes": 17770, "code": "C's", "name": "CIUDADANOS-PARTIDO DE LA CIUDADAN\u00cdA", "seats": 0}, {"acronym": "unio.cat", "votes": 4839, "code": "Unio", "name": "UNI\u00d3 DEMOCR\u00c0TICA DE CATALUNYA", "seats": 0}, {"acronym": "PACMA", "votes": 1763, "code": "PACMA", "name": "PARTIDO ANIMALISTA CONTRA EL MALTRATO ANIMAL", "seats": 0}, {"acronym": "UPYD", "votes": 774, "code": "UPYD", "name": "UNI\u00d3N PROGRESO Y DEMOCRACIA", "seats": 0}, {"acronym": "VOX", "votes": 491, "code": "VOX", "name": "VOX", "seats": 0}, {"acronym": "RECORTES CERO-GRUPO VERDE", "votes": 391, "code": "Recortes Cero", "name": "RECORTES CERO-GRUPO VERDE", "seats": 0}, {"acronym": "PCPC", "votes": 311, "code": "PC", "name": "PARTIT COMUNISTA DEL POBLE DE CATALUNYA", "seats": 0}], "community": "CA09", "province_number": "25", "totalseats": 4, "blank": 2121, "null": 1827}, {"province": "Rioja, La", "absent": 54421, "census": 233085, "voters": 178664, "parties": [{"acronym": "PP", "votes": 67736, "code": "PP", "name": "PARTIDO POPULAR", "seats": 2}, {"acronym": "PSOE", "votes": 41875, "code": "PSOE", "name": "PARTIDO SOCIALISTA OBRERO ESPA\u00d1OL", "seats": 1}, {"acronym": "PODEMOS", "votes": 27941, "code": "PODEMOS", "name": "PODEMOS", "seats": 1}, {"acronym": "C's", "votes": 26719, "code": "C's", "name": "CIUDADANOS-PARTIDO DE LA CIUDADAN\u00cdA", "seats": 0}, {"acronym": "IU-UPeC", "votes": 7397, "code": "UP", "name": "UNIDAD POPULAR: IZQUIERDA UNIDA, UNIDAD POPULAR EN COM\u00daN", "seats": 0}, {"acronym": "UPYD", "votes": 1349, "code": "UPYD", "name": "UNI\u00d3N PROGRESO Y DEMOCRACIA", "seats": 0}, {"acronym": "PACMA", "votes": 1165, "code": "PACMA", "name": "PARTIDO ANIMALISTA CONTRA EL MALTRATO ANIMAL", "seats": 0}, {"acronym": "EB", "votes": 357, "code": "EB", "name": "ESCA\u00d1OS EN BLANCO", "seats": 0}, {"acronym": "RECORTES CERO-GRUPO VERDE", "votes": 356, "code": "Recortes Cero", "name": "RECORTES CERO-GRUPO VERDE", "seats": 0}, {"acronym": "PCPE", "votes": 228, "code": "PC", "name": "PARTIDO COMUNISTA DE LOS PUEBLOS DE ESPA\u00d1A", "seats": 0}], "community": "CA17", "province_number": "26", "totalseats": 4, "blank": 1492, "null": 2049}, {"province": "Lugo", "absent": 80724, "census": 286313, "voters": 205589, "parties": [{"acronym": "PP", "votes": 85810, "code": "PP", "name": "PARTIDO POPULAR", "seats": 2}, {"acronym": "PSdeG-PSOE", "votes": 48413, "code": "PSOE", "name": "PARTIDO DOS SOCIALISTAS DE GALICIA-PSOE", "seats": 1}, {"acronym": "PODEMOS-EN MAREA-ANOVA-EU", "votes": 38873, "code": "PODEMOS", "name": "EN MAREA", "seats": 1}, {"acronym": "C's", "votes": 15346, "code": "C's", "name": "CIUDADANOS-PARTIDO DE LA CIUDADAN\u00cdA", "seats": 0}, {"acronym": "N\u00d3S", "votes": 7208, "code": "BNG", "name": "N\u00d3S-CANDIDATURA GALEGA (BNG-CG-FOGA-PCPG-PG)", "seats": 0}, {"acronym": "PACMA", "votes": 1580, "code": "PACMA", "name": "PARTIDO ANIMALISTA CONTRA EL MALTRATO ANIMAL", "seats": 0}, {"acronym": "UPYD", "votes": 954, "code": "UPYD", "name": "UNI\u00d3N PROGRESO Y DEMOCRACIA", "seats": 0}, {"acronym": "RECORTES CERO-GRUPO VERDE", "votes": 431, "code": "Recortes Cero", "name": "RECORTES CERO-GRUPO VERDE", "seats": 0}, {"acronym": "PCPE", "votes": 417, "code": "PC", "name": "COMUNISTAS DA GALIZA-PCPE", "seats": 0}, {"acronym": "PT", "votes": 394, "code": "PT", "name": "PARTIDO DA TERRA", "seats": 0}], "community": "CA12", "province_number": "27", "totalseats": 4, "blank": 2436, "null": 3727}, {"province": "Madrid", "absent": 1036370, "census": 4658367, "voters": 3621997, "parties": [{"acronym": "PP", "votes": 1204059, "code": "PP", "name": "PARTIDO POPULAR", "seats": 13}, {"acronym": "PODEMOS", "votes": 750607, "code": "PODEMOS", "name": "PODEMOS", "seats": 8}, {"acronym": "C's", "votes": 676484, "code": "C's", "name": "CIUDADANOS-PARTIDO DE LA CIUDADAN\u00cdA", "seats": 7}, {"acronym": "PSOE", "votes": 643244, "code": "PSOE", "name": "PARTIDO SOCIALISTA OBRERO ESPA\u00d1OL", "seats": 6}, {"acronym": "IU-UPeC", "votes": 189265, "code": "UP", "name": "UNIDAD POPULAR: IZQUIERDA UNIDA, UNIDAD POPULAR EN COM\u00daN", "seats": 2}, {"acronym": "UPYD", "votes": 43110, "code": "UPYD", "name": "UNI\u00d3N PROGRESO Y DEMOCRACIA", "seats": 0}, {"acronym": "PACMA", "votes": 28312, "code": "PACMA", "name": "PARTIDO ANIMALISTA CONTRA EL MALTRATO ANIMAL", "seats": 0}, {"acronym": "VOX", "votes": 22461, "code": "VOX", "name": "VOX", "seats": 0}, {"acronym": "X LA IZQUIERDA-LOS VERDES", "votes": 5007, "code": "Partido X", "name": "X LA IZQUIERDA-LOS VERDES", "seats": 0}, {"acronym": "FE de las JONS", "votes": 4691, "code": "FE", "name": "FALANGE ESPA\u00d1OLA DE LAS JONS", "seats": 0}, {"acronym": "RECORTES CERO-GRUPO VERDE", "votes": 4014, "code": "Recortes Cero", "name": "RECORTES CERO-GRUPO VERDE", "seats": 0}, {"acronym": "PUM+J", "votes": 2834, "code": "PUM+J", "name": "POR UN MUNDO M\u00c1S JUSTO", "seats": 0}, {"acronym": "PH", "votes": 1849, "code": "PH", "name": "PARTIDO HUMANISTA", "seats": 0}, {"acronym": "PCPE", "votes": 1732, "code": "PC", "name": "PARTIDO COMUNISTA DE LOS PUEBLOS DE ESPA\u00d1A", "seats": 0}, {"acronym": "SAIn", "votes": 1230, "code": "SAIn", "name": "SOLIDARIDAD Y AUTOGESTI\u00d3N INTERNACIONALISTA", "seats": 0}, {"acronym": "P-LIB", "votes": 1056, "code": "P-LIB", "name": "PARTIDO LIBERTARIO", "seats": 0}], "community": "CA13", "province_number": "28", "totalseats": 36, "blank": 18729, "null": 23313}, {"province": "M\u00e1laga", "absent": 333058, "census": 1113945, "voters": 780887, "parties": [{"acronym": "PP", "votes": 224282, "code": "PP", "name": "PARTIDO POPULAR", "seats": 4}, {"acronym": "PSOE", "votes": 208405, "code": "PSOE", "name": "PARTIDO SOCIALISTA OBRERO ESPA\u00d1OL", "seats": 3}, {"acronym": "PODEMOS", "votes": 132345, "code": "PODEMOS", "name": "PODEMOS", "seats": 2}, {"acronym": "C's", "votes": 132185, "code": "C's", "name": "CIUDADANOS-PARTIDO DE LA CIUDADAN\u00cdA", "seats": 2}, {"acronym": "IULV-CA, UPeC", "votes": 52647, "code": "UP", "name": "UNIDAD POPULAR: IZQUIERDA UNIDA LOS VERDES-CONVOCATORIA POR ANDALUC\u00cdA, UNIDAD POPULAR EN COM\u00daN", "seats": 0}, {"acronym": "PACMA", "votes": 8836, "code": "PACMA", "name": "PARTIDO ANIMALISTA CONTRA EL MALTRATO ANIMAL", "seats": 0}, {"acronym": "UPYD", "votes": 4488, "code": "UPYD", "name": "UNI\u00d3N PROGRESO Y DEMOCRACIA", "seats": 0}, {"acronym": "VOX", "votes": 1806, "code": "VOX", "name": "VOX", "seats": 0}, {"acronym": "PCPE", "votes": 1020, "code": "PC", "name": "PARTIDO COMUNISTA DE LOS PUEBLOS DE ESPA\u00d1A", "seats": 0}, {"acronym": "RECORTES CERO-GRUPO VERDE", "votes": 963, "code": "Recortes Cero", "name": "RECORTES CERO-GRUPO VERDE", "seats": 0}, {"acronym": "mlgXS\u00cd", "votes": 924, "code": "MALAGAPORSI", "name": "M\u00c1LAGA POR S\u00cd", "seats": 0}, {"acronym": "SOLUCIONA", "votes": 406, "code": "SOLUCIONA", "name": "SOLUCIONA", "seats": 0}, {"acronym": "P-LIB", "votes": 285, "code": "P-LIB", "name": "PARTIDO LIBERTARIO", "seats": 0}], "community": "CA01", "province_number": "29", "totalseats": 11, "blank": 5710, "null": 6585}, {"province": "Murcia", "absent": 271463, "census": 1003794, "voters": 732331, "parties": [{"acronym": "PP", "votes": 293546, "code": "PP", "name": "PARTIDO POPULAR", "seats": 5}, {"acronym": "PSOE", "votes": 147524, "code": "PSOE", "name": "PARTIDO SOCIALISTA OBRERO ESPA\u00d1OL", "seats": 2}, {"acronym": "C\u00b4s", "votes": 128294, "code": "C's", "name": "CIUDADANOS-PARTIDO DE LA CIUDADAN\u00cdA", "seats": 2}, {"acronym": "PODEMOS", "votes": 110089, "code": "PODEMOS", "name": "PODEMOS", "seats": 1}, {"acronym": "UPeC-IU", "votes": 22710, "code": "UP", "name": "UNIDAD POPULAR: UNIDAD POPULAR EN COM\u00daN, IZQUIERDA UNIDA-VERDES", "seats": 0}, {"acronym": "PACMA", "votes": 6561, "code": "PACMA", "name": "PARTIDO ANIMALISTA CONTRA EL MALTRATO ANIMAL", "seats": 0}, {"acronym": "UPYD", "votes": 5418, "code": "UPYD", "name": "UNI\u00d3N PROGRESO Y DEMOCRACIA", "seats": 0}, {"acronym": "VOX", "votes": 3271, "code": "VOX", "name": "VOX", "seats": 0}, {"acronym": "RECORTES CERO-GRUPO VERDE", "votes": 1259, "code": "Recortes Cero", "name": "RECORTES CERO-GRUPO VERDE", "seats": 0}, {"acronym": "EB", "votes": 1062, "code": "EB", "name": "ESCA\u00d1OS EN BLANCO", "seats": 0}, {"acronym": "PCPE", "votes": 1043, "code": "PC", "name": "PARTIDO COMUNISTA DE LOS PUEBLOS DE ESPA\u00d1A", "seats": 0}, {"acronym": "SAIn", "votes": 375, "code": "SAIn", "name": "SOLIDARIDAD Y AUTOGESTI\u00d3N INTERNACIONALISTA", "seats": 0}, {"acronym": "+MAS+", "votes": 309, "code": "+MAS+", "name": "MUERTE AL SISTEMA", "seats": 0}], "community": "CA14", "province_number": "30", "totalseats": 10, "blank": 4492, "null": 6378}, {"province": "Navarra", "absent": 123033, "census": 478332, "voters": 355299, "parties": [{"acronym": "UPN-PP", "votes": 101901, "code": "PP", "name": "UNI\u00d3N DEL PUEBLO NAVARRO EN COALICI\u00d3N CON EL PARTIDO POPULAR", "seats": 2}, {"acronym": "PODEMOS", "votes": 80961, "code": "PODEMOS", "name": "PODEMOS", "seats": 2}, {"acronym": "PSOE", "votes": 54700, "code": "PSOE", "name": "PARTIDO SOCIALISTA OBRERO ESPA\u00d1OL", "seats": 1}, {"acronym": "EH Bildu", "votes": 34856, "code": "Bildu", "name": "EUSKAL HERRIA BILDU", "seats": 0}, {"acronym": "GBAI", "votes": 30554, "code": "GBAI", "name": "GEROA BAI", "seats": 0}, {"acronym": "C\u00b4s", "votes": 24815, "code": "C's", "name": "CIUDADANOS, PARTIDO DE LA CIUDADAN\u00cdA", "seats": 0}, {"acronym": "IU-B-UPeC", "votes": 14489, "code": "UP", "name": "UNIDAD POPULAR-ORAIN BATERA:IZQUIERDA UNIDA, BATZARRE, UNIDAD POPULAR EN COM\u00daN", "seats": 0}, {"acronym": "PACMA", "votes": 2333, "code": "PACMA", "name": "PARTIDO ANIMALISTA CONTRA EL MALTRATO ANIMAL", "seats": 0}, {"acronym": "UPYD", "votes": 1444, "code": "UPYD", "name": "UNI\u00d3N PROGRESO Y DEMOCRACIA", "seats": 0}, {"acronym": "RECORTES CERO-GRUPO VERDE", "votes": 951, "code": "Recortes Cero", "name": "RECORTES CERO-GRUPO VERDE", "seats": 0}, {"acronym": "SAIn", "votes": 909, "code": "SAIn", "name": "SOLIDARIDAD Y AUTOGESTI\u00d3N INTERNACIONALISTA", "seats": 0}, {"acronym": "Ln", "votes": 574, "code": "Ln", "name": "LIBERTAD NAVARRA, LIBERTATE NAFARRA", "seats": 0}], "community": "CA15", "province_number": "31", "totalseats": 5, "blank": 3699, "null": 3113}, {"province": "Ourense", "absent": 74257, "census": 267702, "voters": 193445, "parties": [{"acronym": "PP", "votes": 85729, "code": "PP", "name": "PARTIDO POPULAR", "seats": 2}, {"acronym": "PSdeG-PSOE", "votes": 44298, "code": "PSOE", "name": "PARTIDO DOS SOCIALISTAS DE GALICIA-PSOE", "seats": 1}, {"acronym": "PODEMOS-En Marea-ANOVA-EU", "votes": 34048, "code": "PODEMOS", "name": "EN MAREA", "seats": 1}, {"acronym": "C\u00b4s", "votes": 15020, "code": "C's", "name": "CIUDADANOS PARTIDO DE LA CIUDADAN\u00cdA", "seats": 0}, {"acronym": "N\u00d3S", "votes": 6372, "code": "BNG", "name": "N\u00d3S-CANDIDATURA GALEGA (BNG-CG-FOGA-PCPG-PG)", "seats": 0}, {"acronym": "PACMA", "votes": 1332, "code": "PACMA", "name": "PARTIDO ANIMALISTA CONTRA EL MALTRATO ANIMAL", "seats": 0}, {"acronym": "X ESQ", "votes": 864, "code": "Partido X", "name": "X A ESQUERDA", "seats": 0}, {"acronym": "UPYD", "votes": 789, "code": "UPYD", "name": "UNI\u00d3N PROGRESO Y DEMOCRACIA", "seats": 0}, {"acronym": "RECORTES CERO-GRUPO VERDE", "votes": 382, "code": "Recortes Cero", "name": "RECORTES CERO-GRUPO VERDE", "seats": 0}, {"acronym": "PT", "votes": 332, "code": "PT", "name": "PARTIDO DA TERRA", "seats": 0}], "community": "CA12", "province_number": "32", "totalseats": 4, "blank": 1737, "null": 2542}, {"province": "Asturias", "absent": 252233, "census": 876170, "voters": 623937, "parties": [{"acronym": "PP-FORO", "votes": 186586, "code": "PP", "name": "PARTIDO POPULAR-FORO", "seats": 3}, {"acronym": "PSOE", "votes": 144017, "code": "PSOE", "name": "PARTIDO SOCIALISTA OBRERO ESPA\u00d1OL", "seats": 2}, {"acronym": "PODEMOS", "votes": 132007, "code": "PODEMOS", "name": "PODEMOS", "seats": 2}, {"acronym": "C's", "votes": 83885, "code": "C's", "name": "CIUDADANOS-PARTIDO DE LA CIUDADAN\u00cdA", "seats": 1}, {"acronym": "IU-UPeC-IAS", "votes": 52316, "code": "UP", "name": "UNIDAD POPULAR: IZQUIERDA UNIDA, UNIDAD POPULAR EN COM\u00daN, IZQUIERDA ASTURIANA", "seats": 0}, {"acronym": "PACMA", "votes": 4482, "code": "PACMA", "name": "PARTIDO ANIMALISTA CONTRA EL MALTRATO ANIMAL", "seats": 0}, {"acronym": "UPYD", "votes": 3792, "code": "UPYD", "name": "UNI\u00d3N PROGRESO Y DEMOCRACIA", "seats": 0}, {"acronym": "EB", "votes": 1861, "code": "EB", "name": "ESCA\u00d1OS EN BLANCO", "seats": 0}, {"acronym": "VOX", "votes": 1684, "code": "VOX", "name": "VOX", "seats": 0}, {"acronym": "PCPE", "votes": 1229, "code": "PC", "name": "PARTIDO COMUNISTA DE LOS PUEBLOS DE ESPA\u00d1A", "seats": 0}, {"acronym": "RECORTES CERO-GRUPO VERDE", "votes": 1008, "code": "Recortes Cero", "name": "RECORTES CERO-GRUPO VERDE", "seats": 0}, {"acronym": "PH", "votes": 386, "code": "PH", "name": "PARTIDO HUMANISTA", "seats": 0}], "community": "CA03", "province_number": "33", "totalseats": 8, "blank": 5553, "null": 5131}, {"province": "Palencia", "absent": 31950, "census": 137516, "voters": 105566, "parties": [{"acronym": "PP", "votes": 42072, "code": "PP", "name": "PARTIDO POPULAR", "seats": 2}, {"acronym": "PSOE", "votes": 25613, "code": "PSOE", "name": "PARTIDO SOCIALISTA OBRERO ESPA\u00d1OL", "seats": 1}, {"acronym": "C's", "votes": 14767, "code": "C's", "name": "CIUDADANOS-PARTIDO DE LA CIUDADAN\u00cdA", "seats": 0}, {"acronym": "PODEMOS", "votes": 13981, "code": "PODEMOS", "name": "PODEMOS", "seats": 0}, {"acronym": "IU-UPeC", "votes": 4682, "code": "UP", "name": "UNIDAD POPULAR: IZQUIERDA UNIDA, UNIDAD POPULAR EN COM\u00daN", "seats": 0}, {"acronym": "UPYD", "votes": 821, "code": "UPYD", "name": "UNI\u00d3N PROGRESO Y DEMOCRACIA", "seats": 0}, {"acronym": "PACMA", "votes": 614, "code": "PACMA", "name": "PARTIDO ANIMALISTA CONTRA EL MALTRATO ANIMAL", "seats": 0}, {"acronym": "FE de las JONS", "votes": 217, "code": "FE", "name": "FALANGE ESPA\u00d1OLA DE LAS JONS", "seats": 0}, {"acronym": "EB", "votes": 180, "code": "EB", "name": "ESCA\u00d1OS EN BLANCO", "seats": 0}, {"acronym": "RECORTES CERO-GRUPO VERDE", "votes": 157, "code": "Recortes Cero", "name": "RECORTES CERO-GRUPO VERDE", "seats": 0}, {"acronym": "PCPE", "votes": 126, "code": "PC", "name": "PARTIDO COMUNISTA DE LOS PUEBLOS DE ESPA\u00d1A", "seats": 0}, {"acronym": "SAIn", "votes": 70, "code": "SAIn", "name": "SOLIDARIDAD Y AUTOGESTI\u00d3N INTERNACIONALISTA", "seats": 0}], "community": "CA07", "province_number": "34", "totalseats": 3, "blank": 991, "null": 1275}, {"province": "Palmas, Las", "absent": 275265, "census": 798138, "voters": 522873, "parties": [{"acronym": "PP", "votes": 145240, "code": "PP", "name": "PARTIDO POPULAR", "seats": 3}, {"acronym": "PODEMOS", "votes": 136278, "code": "PODEMOS", "name": "PODEMOS", "seats": 2}, {"acronym": "PSOE-NCa", "votes": 115431, "code": "PSOE", "name": "PARTIDO SOCIALISTA OBRERO ESPA\u00d1OL-NUEVA CANARIAS", "seats": 2}, {"acronym": "C's", "votes": 63247, "code": "C's", "name": "CIUDADANOS-PARTIDO DE LA CIUDADAN\u00cdA", "seats": 1}, {"acronym": "CCa-PNC", "votes": 21755, "code": "CCa", "name": "COALICI\u00d3N CANARIA - PARTIDO NACIONALISTA CANARIO", "seats": 0}, {"acronym": "IU-UPeC", "votes": 15235, "code": "UP", "name": "UNIDAD POPULAR: IZQUIERDA UNIDA. UNIDAD POPULAR EN COM\u00daN", "seats": 0}, {"acronym": "PACMA", "votes": 5348, "code": "PACMA", "name": "PARTIDO ANIMALISTA CONTRA EL MALTRATO ANIMAL", "seats": 0}, {"acronym": "UPYD", "votes": 2557, "code": "UPYD", "name": "UNI\u00d3N PROGRESO Y DEMOCRACIA", "seats": 0}, {"acronym": "CANARIAS DECIDE", "votes": 1599, "code": "Canarias Decide", "name": "CANARIAS DECIDE: LOS VERDES, UNIDAD DEL PUEBLO Y ALTERNATIVA REPUBLICANA", "seats": 0}, {"acronym": "RECORTES CERO-GRUPO VERDE", "votes": 1473, "code": "Recortes Cero", "name": "RECORTES CERO-GRUPO VERDE", "seats": 0}, {"acronym": "PCPC", "votes": 953, "code": "PC", "name": "PARTIDO COMUNISTA DEL PUEBLO CANARIO", "seats": 0}, {"acronym": "VOX", "votes": 771, "code": "VOX", "name": "VOX", "seats": 0}, {"acronym": "PUM+J", "votes": 611, "code": "PUM+J", "name": "POR UN MUNDO M\u00c1S JUSTO", "seats": 0}, {"acronym": "PH", "votes": 438, "code": "PH", "name": "PARTIDO HUMANISTA", "seats": 0}, {"acronym": "SAIn", "votes": 299, "code": "SAIn", "name": "SOLIDARIDAD Y AUTOGESTI\u00d3N INTERNACIONALISTA", "seats": 0}], "community": "CA05", "province_number": "35", "totalseats": 8, "blank": 4110, "null": 7528}, {"province": "Pontevedra", "absent": 198871, "census": 774938, "voters": 576067, "parties": [{"acronym": "PP", "votes": 195802, "code": "PP", "name": "PARTIDO POPULAR", "seats": 3}, {"acronym": "PODEMOS-En Marea-ANOVA-EU", "votes": 158824, "code": "PODEMOS", "name": "EN MAREA", "seats": 2}, {"acronym": "PSdeG-PSOE", "votes": 118300, "code": "PSOE", "name": "PARTIDO DOS SOCIALISTAS DE GALICIA-PSOE", "seats": 2}, {"acronym": "C's", "votes": 51149, "code": "C's", "name": "CIUDADANOS-PARTIDO DE LA CIUDADAN\u00cdA", "seats": 0}, {"acronym": "N\u00d3S", "votes": 26396, "code": "BNG", "name": "N\u00d3S-CANDIDATURA GALEGA (BNG-CG-FOGA-PCPG-PG)", "seats": 0}, {"acronym": "PACMA", "votes": 5215, "code": "PACMA", "name": "PARTIDO ANIMALISTA CONTRA O MALTRATO ANIMAL", "seats": 0}, {"acronym": "UPYD", "votes": 3144, "code": "UPYD", "name": "UNI\u00d3N PROGRESO Y DEMOCRACIA", "seats": 0}, {"acronym": "RECORTES CERO-GRUPO VERDE", "votes": 1412, "code": "Recortes Cero", "name": "RECORTES CERO-GRUPO VERDE", "seats": 0}, {"acronym": "PCPE", "votes": 1358, "code": "PC", "name": "COMUNISTAS DA GALIZA", "seats": 0}, {"acronym": "PT", "votes": 1135, "code": "PT", "name": "PARTIDO DA TERRA", "seats": 0}], "community": "CA12", "province_number": "36", "totalseats": 7, "blank": 5462, "null": 7870}, {"province": "Salamanca", "absent": 70422, "census": 280763, "voters": 210341, "parties": [{"acronym": "PP", "votes": 88934, "code": "PP", "name": "PARTIDO POPULAR", "seats": 2}, {"acronym": "PSOE", "votes": 45246, "code": "PSOE", "name": "PARTIDO SOCIALISTA OBRERO ESPA\u00d1OL", "seats": 1}, {"acronym": "C's", "votes": 35055, "code": "C's", "name": "CIUDADANOS-PARTIDO DE LA CIUDADAN\u00cdA", "seats": 1}, {"acronym": "PODEMOS", "votes": 25463, "code": "PODEMOS", "name": "PODEMOS", "seats": 0}, {"acronym": "IU-UPeC", "votes": 6972, "code": "UP", "name": "UNIDAD POPULAR: IZQUIERDA UNIDA, UNIDAD POPULAR EN COM\u00daN", "seats": 0}, {"acronym": "UPYD", "votes": 1647, "code": "UPYD", "name": "UNI\u00d3N PROGRESO Y DEMOCRACIA", "seats": 0}, {"acronym": "PACMA", "votes": 1132, "code": "PACMA", "name": "PARTIDO ANIMALISTA CONTRA EL MALTRATO ANIMAL", "seats": 0}, {"acronym": "VOX", "votes": 811, "code": "VOX", "name": "VOX", "seats": 0}, {"acronym": "RECORTES CERO-GRUPO VERDE", "votes": 312, "code": "Recortes Cero", "name": "RECORTES CERO-GRUPO VERDE", "seats": 0}, {"acronym": "PCPE", "votes": 262, "code": "PC", "name": "PARTIDO COMUNISTA DE LOS PUEBLOS DE ESPA\u00d1A", "seats": 0}, {"acronym": "PREPAL", "votes": 240, "code": "PREPAL", "name": "PARTIDO REGIONALISTA DEL PA\u00cdS LEON\u00c9S", "seats": 0}], "community": "CA07", "province_number": "37", "totalseats": 4, "blank": 1993, "null": 2274}, {"province": "Santa Cruz de Tenerife", "absent": 250714, "census": 733349, "voters": 482635, "parties": [{"acronym": "PP", "votes": 138072, "code": "PP", "name": "PARTIDO POPULAR", "seats": 2}, {"acronym": "PSOE-NCa", "votes": 102810, "code": "PSOE", "name": "PARTIDO SOCIALISTA OBRERO ESPA\u00d1OL-NUEVA CANARIAS", "seats": 2}, {"acronym": "PODEMOS", "votes": 94785, "code": "PODEMOS", "name": "PODEMOS", "seats": 1}, {"acronym": "CCa-PNC", "votes": 59995, "code": "CCa", "name": "COALICI\u00d3N CANARIA-PARTIDO NACIONALISTA CANARIO", "seats": 1}, {"acronym": "C's", "votes": 50151, "code": "C's", "name": "CIUDADANOS-PARTIDO DE LA CIUDADAN\u00cdA", "seats": 1}, {"acronym": "IUC-UPeC", "votes": 15698, "code": "UP", "name": "UNIDAD POPULAR: IZQUIERDA UNIDA CANARIA, UNIDAD POPULAR EN COM\u00daN", "seats": 0}, {"acronym": "PACMA", "votes": 6526, "code": "PACMA", "name": "PARTIDO ANIMALISTA CONTRA EL MALTRATO ANIMAL", "seats": 0}, {"acronym": "UPYD", "votes": 2109, "code": "UPYD", "name": "UNI\u00d3N PROGRESO Y DEMOCRACIA", "seats": 0}, {"acronym": "CANARIAS DECIDE", "votes": 1275, "code": "Canarias Decide", "name": "CANARIAS DECIDE: LOS VERDES, UNIDAD DEL PUEBLO Y ALTERNATIVA REPUBLICANA", "seats": 0}, {"acronym": "RECORTES CERO-GRUPO VERDE", "votes": 1175, "code": "Recortes Cero", "name": "RECORTES CERO-GRUPO VERDE", "seats": 0}, {"acronym": "VOX", "votes": 769, "code": "VOX", "name": "VOX", "seats": 0}, {"acronym": "PCPC", "votes": 758, "code": "PC", "name": "PARTIDO COMUNISTA DEL PUEBLO CANARIO", "seats": 0}], "community": "CA05", "province_number": "38", "totalseats": 7, "blank": 3150, "null": 5362}, {"province": "Cantabria", "absent": 111387, "census": 464078, "voters": 352691, "parties": [{"acronym": "PP", "votes": 128852, "code": "PP", "name": "PARTIDO POPULAR", "seats": 2}, {"acronym": "PSOE", "votes": 78217, "code": "PSOE", "name": "PARTIDO SOCIALISTA OBRERO ESPA\u00d1OL", "seats": 1}, {"acronym": "PODEMOS", "votes": 62219, "code": "PODEMOS", "name": "PODEMOS", "seats": 1}, {"acronym": "C's", "votes": 53182, "code": "C's", "name": "CIUDADANOS-PARTIDO DE LA CIUDADAN\u00cdA", "seats": 1}, {"acronym": "IU-UPeC", "votes": 15428, "code": "UP", "name": "UNIDAD POPULAR: IZQUIERDA UNIDA, UNIDAD POPULAR EN COM\u00daN", "seats": 0}, {"acronym": "PACMA", "votes": 2924, "code": "PACMA", "name": "PARTIDO ANIMALISTA CONTRA EL MALTRATO ANIMAL", "seats": 0}, {"acronym": "UPYD", "votes": 2860, "code": "UPYD", "name": "UNI\u00d3N PROGRESO Y DEMOCRACIA", "seats": 0}, {"acronym": "VOX", "votes": 895, "code": "VOX", "name": "VOX", "seats": 0}, {"acronym": "RECORTES CERO-GRUPO VERDE", "votes": 522, "code": "Recortes Cero", "name": "RECORTES CERO-GRUPO VERDE", "seats": 0}, {"acronym": "PCPE", "votes": 458, "code": "PC", "name": "PARTIDO COMUNISTA DE LOS PUEBLOS DE ESPA\u00d1A", "seats": 0}, {"acronym": "PH", "votes": 235, "code": "PH", "name": "PARTIDO HUMANISTA", "seats": 0}, {"acronym": "SAIn", "votes": 171, "code": "SAIn", "name": "SOLIDARIDAD Y AUTOGESTI\u00d3N INTERNACIONALISTA", "seats": 0}], "community": "CA06", "province_number": "39", "totalseats": 5, "blank": 2843, "null": 3885}, {"province": "Segovia", "absent": 25605, "census": 118503, "voters": 92898, "parties": [{"acronym": "PP", "votes": 36130, "code": "PP", "name": "PARTIDO POPULAR", "seats": 2}, {"acronym": "PSOE", "votes": 19724, "code": "PSOE", "name": "PARTIDO SOCIALISTA OBRERO ESPA\u00d1OL", "seats": 1}, {"acronym": "C's", "votes": 15625, "code": "C's", "name": "CIUDADANOS-PARTIDO DE LA CIUDADAN\u00cdA", "seats": 0}, {"acronym": "PODEMOS", "votes": 13063, "code": "PODEMOS", "name": "PODEMOS", "seats": 0}, {"acronym": "IU-UPeC", "votes": 3732, "code": "UP", "name": "UNIDAD POPULAR: IZQUIERDA UNIDA, UNIDAD POPULAR EN COM\u00daN, SEGOVIEMOS", "seats": 0}, {"acronym": "UPYD", "votes": 1268, "code": "UPYD", "name": "UNI\u00d3N PROGRESO Y DEMOCRACIA", "seats": 0}, {"acronym": "PACMA", "votes": 513, "code": "PACMA", "name": "PARTIDO ANIMALISTA CONTRA EL MALTRATO ANIMAL", "seats": 0}, {"acronym": "RECORTES CERO-GRUPO VERDE", "votes": 225, "code": "Recortes Cero", "name": "RECORTES CERO-GRUPO VERDE", "seats": 0}, {"acronym": "FE de las JONS", "votes": 223, "code": "FE", "name": "FALANGE ESPA\u00d1OLA DE LAS JONS", "seats": 0}, {"acronym": "PCPE", "votes": 189, "code": "PC", "name": "PARTIDO COMUNISTA DE LOS PUEBLOS DE ESPA\u00d1A", "seats": 0}], "community": "CA07", "province_number": "40", "totalseats": 3, "blank": 910, "null": 1296}, {"province": "Sevilla", "absent": 396654, "census": 1501270, "voters": 1104121, "parties": [{"acronym": "PSOE", "votes": 371103, "code": "PSOE", "name": "PARTIDO SOCIALISTA OBRERO ESPA\u00d1OL", "seats": 5}, {"acronym": "PP", "votes": 275335, "code": "PP", "name": "PARTIDO POPULAR", "seats": 3}, {"acronym": "PODEMOS", "votes": 207826, "code": "PODEMOS", "name": "PODEMOS", "seats": 2}, {"acronym": "C\u00b4s", "votes": 142301, "code": "C's", "name": "CIUDADANOS PARTIDO DE LA CIUDADAN\u00cdA", "seats": 2}, {"acronym": "IULV-CA, UPeC", "votes": 62152, "code": "UP", "name": "UNIDAD POPULAR: IZQUIERDA UNIDA LOS VERDES-CONVOCATORIA POR ANDALUC\u00cdA, UNIDAD POPULAR EN COM\u00daN", "seats": 0}, {"acronym": "PACMA", "votes": 9967, "code": "PACMA", "name": "PARTIDO ANIMALISTA CONTRA EL MALTRATO ANIMAL", "seats": 0}, {"acronym": "UPYD", "votes": 6492, "code": "UPYD", "name": "UNI\u00d3N PROGRESO Y DEMOCRACIA", "seats": 0}, {"acronym": "VOX", "votes": 2704, "code": "VOX", "name": "VOX", "seats": 0}, {"acronym": "RECORTES CERO-GRUPO VERDE", "votes": 1410, "code": "Recortes Cero", "name": "RECORTES CERO-GRUPO VERDE", "seats": 0}, {"acronym": "PCOE", "votes": 1096, "code": "PC", "name": "PARTIDO COMUNISTA OBRERO ESPA\u00d1OL", "seats": 0}, {"acronym": "FE de las JONS", "votes": 988, "code": "FE", "name": "FALANGE ESPA\u00d1OLA DE LAS JONS", "seats": 0}, {"acronym": "PCPE", "votes": 891, "code": "PC", "name": "PARTIDO COMUNISTA DE LOS PUEBLOS DE ESPA\u00d1A", "seats": 0}, {"acronym": "P-LIB", "votes": 660, "code": "P-LIB", "name": "PARTIDO LIBERTARIO", "seats": 0}], "community": "CA01", "province_number": "41", "totalseats": 12, "blank": 9975, "null": 11221}, {"province": "Soria", "absent": 18508, "census": 70718, "voters": 52210, "parties": [{"acronym": "PP", "votes": 19934, "code": "PP", "name": "PARTIDO POPULAR", "seats": 1}, {"acronym": "PSOE", "votes": 12280, "code": "PSOE", "name": "PARTIDO SOCIALISTA OBRERO ESPA\u00d1OL", "seats": 1}, {"acronym": "PODEMOS", "votes": 8267, "code": "PODEMOS", "name": "PODEMOS", "seats": 0}, {"acronym": "C\u00b4s", "votes": 7821, "code": "C's", "name": "CIUDADANOS-PARTIDO DE LA CIUDADAN\u00cdA", "seats": 0}, {"acronym": "IU-UPeC", "votes": 1833, "code": "UP", "name": "UNIDAD POPULAR: IZQUIERDA UNIDA, UNIDAD POPULAR EN COM\u00daN", "seats": 0}, {"acronym": "UPYD", "votes": 325, "code": "UPYD", "name": "UNI\u00d3N PROGRESO Y DEMOCRACIA", "seats": 0}, {"acronym": "PACMA", "votes": 187, "code": "PACMA", "name": "PARTIDO ANIMALISTA CONTRA EL MALTRATO ANIMAL", "seats": 0}, {"acronym": "DN", "votes": 100, "code": "DN", "name": "DEMOCRACIA NACIONAL", "seats": 0}, {"acronym": "RECORTES CERO-GRUPO VERDE", "votes": 85, "code": "Recortes Cero", "name": "RECORTES CERO-GRUPO VERDE", "seats": 0}, {"acronym": "PCPE", "votes": 54, "code": "PC", "name": "PARTIDO COMUNISTA DE LOS PUEBLOS DE ESPA\u00d1A", "seats": 0}], "community": "CA07", "province_number": "42", "totalseats": 2, "blank": 678, "null": 646}, {"province": "Tarragona", "absent": 172574, "census": 547970, "voters": 375396, "parties": [{"acronym": "EN COM\u00da", "votes": 76828, "code": "PODEMOS", "name": "EN COM\u00da PODEM", "seats": 1}, {"acronym": "ERC-CATSI", "votes": 65037, "code": "ERC", "name": "ESQUERRA REPUBLICANA DE CATALUNYA-CATALUNYA S\u00cd", "seats": 1}, {"acronym": "PSC", "votes": 58787, "code": "PSOE", "name": "PARTIT DELS SOCIALISTES DE CATALUNYA (PSC-PSOE)", "seats": 1}, {"acronym": "DL", "votes": 56949, "code": "DL", "name": "DEMOCR\u00c0CIA I LLIBERTAT. CONVERG\u00c8NCIA. DEM\u00d2CRATES. REAGRUPAMENT", "seats": 1}, {"acronym": "C's", "votes": 52942, "code": "C's", "name": "CIUDADANOS-PARTIDO DE LA CIUDADAN\u00cdA", "seats": 1}, {"acronym": "PP", "votes": 45477, "code": "PP", "name": "PARTIDO POPULAR", "seats": 1}, {"acronym": "Unio.Cat", "votes": 6299, "code": "Unio", "name": "UNI\u00d3 DEMOCR\u00c0TICA DE CATALUNYA", "seats": 0}, {"acronym": "PACMA", "votes": 4157, "code": "PACMA", "name": "PARTIDO ANIMALISTA CONTRA EL MALTRATO ANIMAL", "seats": 0}, {"acronym": "RECORTES CERO-GRUPO VERDE", "votes": 886, "code": "Recortes Cero", "name": "RECORTES CERO-GRUPO VERDE", "seats": 0}, {"acronym": "PCPC", "votes": 698, "code": "PC", "name": "PARTIT COMUNISTA DEL POBLE DE CATALUNYA", "seats": 0}, {"acronym": "UPYD", "votes": 682, "code": "UPYD", "name": "UNI\u00d3N PROGRESO Y DEMOCRACIA", "seats": 0}, {"acronym": "EB", "votes": 618, "code": "EB", "name": "ESCONS EN BLANC/ESCA\u00d1OS EN BLANCO", "seats": 0}], "community": "CA09", "province_number": "43", "totalseats": 6, "blank": 2679, "null": 3357}, {"province": "Teruel", "absent": 26952, "census": 105452, "voters": 78500, "parties": [{"acronym": "PP-PAR", "votes": 28224, "code": "PP", "name": "PARTIDO POPULAR EN COALICI\u00d3N CON EL PARTIDO ARAGON\u00c9S", "seats": 2}, {"acronym": "PSOE", "votes": 19854, "code": "PSOE", "name": "PARTIDO SOCIALISTA OBRERO ESPA\u00d1OL", "seats": 1}, {"acronym": "PODEMOS", "votes": 11806, "code": "PODEMOS", "name": "PODEMOS", "seats": 0}, {"acronym": "C's", "votes": 11400, "code": "C's", "name": "CIUDADANOS-PARTIDO DE LA CIUDADAN\u00cdA", "seats": 0}, {"acronym": "IU-CHA-UPeC", "votes": 3873, "code": "UP", "name": "UNIDAD POPULAR EN ARAG\u00d3N: IZQUIERDA UNIDA, CHUNTA ARAGONESISTA, UNIDAD POPULAR EN COM\u00daN", "seats": 0}, {"acronym": "UPYD", "votes": 449, "code": "UPYD", "name": "UNI\u00d3N PROGRESO Y DEMOCRACIA", "seats": 0}, {"acronym": "PACMA", "votes": 375, "code": "PACMA", "name": "PARTIDO ANIMALISTA CONTRA EL MALTRATO ANIMAL", "seats": 0}, {"acronym": "EB", "votes": 317, "code": "EB", "name": "ESCA\u00d1OS EN BLANCO", "seats": 0}, {"acronym": "RECORTES CERO-GRUPO VERDE", "votes": 135, "code": "Recortes Cero", "name": "RECORTES CERO-GRUPO VERDE", "seats": 0}, {"acronym": "PCPE", "votes": 105, "code": "PC", "name": "PARTIDO COMUNISTA DE LOS PUEBLOS DE ESPA\u00d1A", "seats": 0}], "community": "CA02", "province_number": "44", "totalseats": 3, "blank": 883, "null": 1079}, {"province": "Toledo", "absent": 119617, "census": 509327, "voters": 389710, "parties": [{"acronym": "PP", "votes": 149274, "code": "PP", "name": "PARTIDO POPULAR", "seats": 2}, {"acronym": "PSOE", "votes": 106842, "code": "PSOE", "name": "PARTIDO SOCIALISTA OBRERO ESPA\u00d1OL", "seats": 2}, {"acronym": "C's", "votes": 53095, "code": "C's", "name": "CIUDADANOS-PARTIDO DE LA CIUDADAN\u00cdA", "seats": 1}, {"acronym": "PODEMOS", "votes": 52407, "code": "PODEMOS", "name": "PODEMOS", "seats": 1}, {"acronym": "IU-UPeC", "votes": 13555, "code": "UP", "name": "UNIDAD POPULAR: IZQUIERDA UNIDA, UNIDAD POPULAR EN COM\u00daN", "seats": 0}, {"acronym": "PACMA", "votes": 3029, "code": "PACMA", "name": "PARTIDO ANIMALISTA CONTRA EL MALTRATO ANIMAL", "seats": 0}, {"acronym": "UPYD", "votes": 1891, "code": "UPYD", "name": "UNI\u00d3N PROGRESO Y DEMOCRACIA", "seats": 0}, {"acronym": "VOX", "votes": 1501, "code": "VOX", "name": "VOX", "seats": 0}, {"acronym": "RECORTES CERO-GRUPO VERDE", "votes": 608, "code": "Recortes Cero", "name": "RECORTES CERO-GRUPO VERDE", "seats": 0}, {"acronym": "PCPE", "votes": 304, "code": "PC", "name": "PARTIDO COMUNISTA DE LOS PUEBLOS DE ESPA\u00d1A", "seats": 0}], "community": "CA08", "province_number": "45", "totalseats": 6, "blank": 2324, "null": 4880}, {"province": "Valencia/Val\u00e8ncia", "absent": 418718, "census": 1893207, "voters": 1474489, "parties": [{"acronym": "PP", "votes": 442005, "code": "PP", "name": "PARTIDO POPULAR", "seats": 5}, {"acronym": "PODEMOS-COMPROM\u00cdS", "votes": 395729, "code": "PODEMOS", "name": "COMPROM\u00cdS-PODEMOS-\u00c9S EL MOMENT", "seats": 5}, {"acronym": "PSOE", "votes": 275680, "code": "PSOE", "name": "PARTIDO SOCIALISTA OBRERO ESPA\u00d1OL", "seats": 3}, {"acronym": "C's", "votes": 221299, "code": "C's", "name": "CIUDADANOS-PARTIDO DE LA CIUDADAN\u00cdA", "seats": 2}, {"acronym": "EUPV-UPeC", "votes": 68759, "code": "UP", "name": "UNITAT POPULAR: ESQUERRA UNIDA DEL PA\u00cdS VALENCI\u00c0, UNITAT POPULAR EN COM\u00daN", "seats": 0}, {"acronym": "PACMA", "votes": 14445, "code": "PACMA", "name": "PARTIDO ANIMALISTA CONTRA EL MALTRATO ANIMAL", "seats": 0}, {"acronym": "UPYD", "votes": 9959, "code": "UPYD", "name": "UNI\u00d3N PROGRESO Y DEMOCRACIA", "seats": 0}, {"acronym": "CCD", "votes": 7101, "code": "CCD", "name": "CIUDADANOS DE CENTRO DEMOCR\u00c1TICO", "seats": 0}, {"acronym": "SOMVAL", "votes": 5221, "code": "SOMVAL", "name": "SOM VALENCIANS", "seats": 0}, {"acronym": "VOX", "votes": 4097, "code": "VOX", "name": "VOX", "seats": 0}, {"acronym": "RECORTES CERO-GRUPO VERDE", "votes": 2743, "code": "Recortes Cero", "name": "RECORTES CERO-GRUPO VERDE", "seats": 0}, {"acronym": "PCPE", "votes": 2077, "code": "PC", "name": "PARTIDO COMUNISTA DE LOS PUEBLOS DE ESPA\u00d1A", "seats": 0}, {"acronym": "ARA, PV", "votes": 1469, "code": "ARAPV", "name": "ARA, PA\u00cdS VALENCI\u00c0", "seats": 0}, {"acronym": "EN POSITIU", "votes": 1276, "code": "EN POSITIU", "name": "EN POSITIU", "seats": 0}, {"acronym": "AVANT", "votes": 1001, "code": "AVANT", "name": "AVANT VALENCIANS", "seats": 0}, {"acronym": "IFem", "votes": 999, "code": "IFem", "name": "INICIATIVA FEMINISTA", "seats": 0}], "community": "CA10", "province_number": "46", "totalseats": 15, "blank": 8738, "null": 11891}, {"province": "Valladolid", "absent": 90926, "census": 421369, "voters": 330443, "parties": [{"acronym": "PP", "votes": 121065, "code": "PP", "name": "PARTIDO POPULAR", "seats": 2}, {"acronym": "PSOE", "votes": 70713, "code": "PSOE", "name": "PARTIDO SOCIALISTA OBRERO ESPA\u00d1OL", "seats": 1}, {"acronym": "C's", "votes": 56060, "code": "C's", "name": "CIUDADANOS-PARTIDO DE LA CIUDADAN\u00cdA", "seats": 1}, {"acronym": "PODEMOS", "votes": 49880, "code": "PODEMOS", "name": "PODEMOS", "seats": 1}, {"acronym": "UPeC-IU-IZCA", "votes": 17849, "code": "UP", "name": "UNIDAD POPULAR: IZQUIERDA UNIDA, UNIDAD POPULAR EN COM\u00daN, IZQUIERDA CASTELLANA", "seats": 0}, {"acronym": "UPYD", "votes": 2927, "code": "UPYD", "name": "UNI\u00d3N PROGRESO Y DEMOCRACIA", "seats": 0}, {"acronym": "PACMA", "votes": 1717, "code": "PACMA", "name": "PARTIDO ANIMALISTA CONTRA EL MALTRATO ANIMAL", "seats": 0}, {"acronym": "CCD", "votes": 1570, "code": "CCD", "name": "CIUDADANOS DE CENTRO DEMOCR\u00c1TICO", "seats": 0}, {"acronym": "VOX", "votes": 1224, "code": "VOX", "name": "VOX", "seats": 0}, {"acronym": "RECORTES CERO-GRUPO VERDE", "votes": 482, "code": "Recortes Cero", "name": "RECORTES CERO-GRUPO VERDE", "seats": 0}, {"acronym": "PCPE", "votes": 427, "code": "PC", "name": "PARTIDO COMUNISTA DE LOS PUEBLOS DE ESPA\u00d1A", "seats": 0}, {"acronym": "FE de las JONS", "votes": 408, "code": "FE", "name": "FALANGE ESPA\u00d1OLA DE LAS JONS", "seats": 0}, {"acronym": "DN", "votes": 286, "code": "DN", "name": "DEMOCRACIA NACIONAL", "seats": 0}, {"acronym": "SAIn", "votes": 271, "code": "SAIn", "name": "SOLIDARIDAD Y AUTOGESTI\u00d3N INTERNACIONALISTA", "seats": 0}], "community": "CA07", "province_number": "47", "totalseats": 5, "blank": 2679, "null": 2885}, {"province": "Bizkaia", "absent": 256144, "census": 913239, "voters": 657095, "parties": [{"acronym": "EAJ-PNV", "votes": 182245, "code": "PNV", "name": "EUZKO ALDERDI JELTZALEA-PARTIDO NACIONALISTA VASCO", "seats": 3}, {"acronym": "PODEMOS-AHAL DUGU", "votes": 170317, "code": "PODEMOS", "name": "PODEMOS/AHAL DUGU", "seats": 2}, {"acronym": "PSE-EE (PSOE)", "votes": 84643, "code": "PSOE", "name": "PARTIDO SOCIALISTA DE EUSKADI-EUSKADIKO EZKERRA (PSOE)", "seats": 1}, {"acronym": "EH Bildu", "votes": 81552, "code": "Bildu", "name": "EUSKAL HERRIA BILDU", "seats": 1}, {"acronym": "PP", "votes": 74279, "code": "PP", "name": "PARTIDO POPULAR", "seats": 1}, {"acronym": "C's", "votes": 25000, "code": "C's", "name": "CIUDADANOS-PARTIDO DE LA CIUDADAN\u00cdA", "seats": 0}, {"acronym": "IU-UpeC", "votes": 18391, "code": "UP", "name": "UNIDAD POPULAR-ORAIN BATERA:EZKER ANITZA-IZQUIERDA UNIDA-UNIDAD POPULAR EN COM\u00daN", "seats": 0}, {"acronym": "PACMA", "votes": 4325, "code": "PACMA", "name": "PARTIDO ANIMALISTA CONTRA EL MALTRATO ANIMAL", "seats": 0}, {"acronym": "UPYD", "votes": 1991, "code": "UPYD", "name": "UNI\u00d3N PROGRESO Y DEMOCRACIA", "seats": 0}, {"acronym": "EZKERRA", "votes": 1471, "code": "Partido X", "name": "EZKERRA-X LA IZQUIERDA", "seats": 0}, {"acronym": "RECORTES CERO-GRUPO VERDE", "votes": 1083, "code": "Recortes Cero", "name": "RECORTES CERO-GRUPO VERDE", "seats": 0}, {"acronym": "EB-AZ", "votes": 1035, "code": "EB", "name": "ESCA\u00d1OS EN BLANCO-AULKI ZURIAK", "seats": 0}, {"acronym": "PUM+J", "votes": 475, "code": "PUM+J", "name": "BIDEZKO MUNDURANTZ/POR UN MUNDO M\u00c1S JUSTO", "seats": 0}, {"acronym": "PCPE", "votes": 408, "code": "PC", "name": "PARTIDO COMUNISTA DE LOS PUEBLOS DE ESPA\u00d1A", "seats": 0}, {"acronym": "JS,PC", "votes": 405, "code": "JS,PC", "name": "JUSTIZIA SOCIAL, PARTICIPACI\u00d3N CIUDADANA", "seats": 0}], "community": "CA16", "province_number": "48", "totalseats": 8, "blank": 4820, "null": 4655}, {"province": "Zamora", "absent": 41577, "census": 155511, "voters": 113934, "parties": [{"acronym": "PP", "votes": 47858, "code": "PP", "name": "PARTIDO POPULAR", "seats": 2}, {"acronym": "PSOE", "votes": 25826, "code": "PSOE", "name": "PARTIDO SOCIALISTA OBRERO ESPA\u00d1OL", "seats": 1}, {"acronym": "PODEMOS", "votes": 15727, "code": "PODEMOS", "name": "PODEMOS", "seats": 0}, {"acronym": "C's", "votes": 14527, "code": "C's", "name": "CIUDADANOS-PARTIDO DE LA CIUDADAN\u00cdA", "seats": 0}, {"acronym": "IU-UPeC", "votes": 5490, "code": "UP", "name": "UNIDAD POPULAR: IZQUIERDA UNIDA, UNIDAD POPULAR EN COM\u00daN", "seats": 0}, {"acronym": "UPYD", "votes": 736, "code": "UPYD", "name": "UNI\u00d3N PROGRESO Y DEMOCRACIA", "seats": 0}, {"acronym": "PACMA", "votes": 481, "code": "PACMA", "name": "PARTIDO ANIMALISTA CONTRA EL MALTRATO ANIMAL", "seats": 0}, {"acronym": "PREPAL", "votes": 229, "code": "PREPAL", "name": "PARTIDO REGIONALISTA DEL PA\u00cdS LEON\u00c9S", "seats": 0}, {"acronym": "RECORTES CERO-GRUPO VERDE", "votes": 176, "code": "Recortes Cero", "name": "RECORTES CERO-GRUPO VERDE", "seats": 0}, {"acronym": "PCPE", "votes": 123, "code": "PC", "name": "PARTIDO COMUNISTA DE LOS PUEBLOS DE ESPA\u00d1A", "seats": 0}], "community": "CA07", "province_number": "49", "totalseats": 3, "blank": 1227, "null": 1534}, {"province": "Zaragoza", "absent": 178113, "census": 714366, "voters": 536253, "parties": [{"acronym": "PP-PAR", "votes": 161341, "code": "PP", "name": "PARTIDO POPULAR EN COALICI\u00d3N CON EL PARTIDO ARAGON\u00c9S", "seats": 3}, {"acronym": "PSOE", "votes": 118742, "code": "PSOE", "name": "PARTIDO SOCIALISTA OBRERO ESPA\u00d1OL", "seats": 2}, {"acronym": "PODEMOS", "votes": 102189, "code": "PODEMOS", "name": "PODEMOS", "seats": 1}, {"acronym": "C's", "votes": 94800, "code": "C's", "name": "CIUDADANOS-PARTIDO DE LA CIUDADAN\u00cdA", "seats": 1}, {"acronym": "IU-CHA-UPeC", "votes": 34773, "code": "UP", "name": "UNIDAD POPULAR EN ARAG\u00d3N: IZQUIERDA UNIDA, CHUNTA ARAGONESISTA, UNIDAD POPULAR EN COM\u00daN", "seats": 0}, {"acronym": "UPYD", "votes": 4495, "code": "UPYD", "name": "UNI\u00d3N PROGRESO Y DEMOCRACIA", "seats": 0}, {"acronym": "PACMA", "votes": 4042, "code": "PACMA", "name": "PARTIDO ANIMALISTA CONTRA EL MALTRATO ANIMAL", "seats": 0}, {"acronym": "EB", "votes": 2987, "code": "EB", "name": "ESCA\u00d1OS EN BLANCO", "seats": 0}, {"acronym": "VOX", "votes": 1839, "code": "VOX", "name": "VOX", "seats": 0}, {"acronym": "RECORTES CERO-GRUPO VERDE", "votes": 1079, "code": "Recortes Cero", "name": "RECORTES CERO-GRUPO VERDE", "seats": 0}, {"acronym": "PCPE", "votes": 873, "code": "PC", "name": "PARTIDO COMUNISTA DE LOS PUEBLOS DE ESPA\u00d1A", "seats": 0}, {"acronym": "Independientes-FIA", "votes": 560, "code": "FIA", "name": "INDEPENDIENTES POR ARAG\u00d3N", "seats": 0}], "community": "CA02", "province_number": "50", "totalseats": 7, "blank": 4641, "null": 3892}, {"province": "Ceuta", "absent": 25781, "census": 59213, "voters": 33432, "parties": [{"acronym": "PP", "votes": 14786, "code": "PP", "name": "PARTIDO POPULAR", "seats": 1}, {"acronym": "PSOE", "votes": 7599, "code": "PSOE", "name": "PARTIDO SOCIALISTA OBRERO ESPA\u00d1OL", "seats": 0}, {"acronym": "PODEMOS", "votes": 4630, "code": "PODEMOS", "name": "PODEMOS", "seats": 0}, {"acronym": "C's", "votes": 4378, "code": "C's", "name": "CIUDADANOS-PARTIDO DE LA CIUDADAN\u00cdA", "seats": 0}, {"acronym": "IU-UPeC", "votes": 428, "code": "UP", "name": "UNIDAD POPULAR: IZQUIERDA UNIDA, UNIDAD POPULAR EN COM\u00daN", "seats": 0}, {"acronym": "PACMA", "votes": 356, "code": "PACMA", "name": "PARTIDO ANIMALISTA CONTRA EL MALTRATO ANIMAL", "seats": 0}, {"acronym": "UPYD", "votes": 194, "code": "UPYD", "name": "UNI\u00d3N PROGRESO Y DEMOCRACIA", "seats": 0}, {"acronym": "RECORTES CERO-GRUPO VERDE", "votes": 144, "code": "Recortes Cero", "name": "RECORTES CERO-GRUPO VERDE", "seats": 0}], "community": "CA18", "province_number": "51", "totalseats": 1, "blank": 420, "null": 497}, {"province": "Melilla", "absent": 24872, "census": 53255, "voters": 28383, "parties": [{"acronym": "PP", "votes": 12309, "code": "PP", "name": "PARTIDO POPULAR", "seats": 1}, {"acronym": "PSOE", "votes": 6889, "code": "PSOE", "name": "PARTIDO SOCIALISTA OBRERO ESPA\u00d1OL", "seats": 0}, {"acronym": "C's", "votes": 4356, "code": "C's", "name": "CIUDADANOS-PARTIDO DE LA CIUDADAN\u00cdA", "seats": 0}, {"acronym": "PODEMOS", "votes": 3206, "code": "PODEMOS", "name": "PODEMOS", "seats": 0}, {"acronym": "UNIDAD POPULAR", "votes": 362, "code": "UP", "name": "UNIDAD POPULAR-IZQUIERDA UNIDA", "seats": 0}, {"acronym": "PACMA", "votes": 313, "code": "PACMA", "name": "PARTIDO ANIMALISTA CONTRA EL MALTRATO ANIMAL", "seats": 0}, {"acronym": "UPYD", "votes": 239, "code": "UPYD", "name": "UNI\u00d3N PROGRESO Y DEMOCRACIA", "seats": 0}, {"acronym": "RECORTES CERO-GRUPO VERDE", "votes": 46, "code": "Recortes Cero", "name": "RECORTES CERO-GRUPO VERDE", "seats": 0}], "community": "CA19", "province_number": "52", "totalseats": 1, "blank": 300, "null": 363}]